{
"meta":{"test_sets":[],"test_metrics":[],"learn_metrics":[{"best_value":"Min","name":"RMSE"}],"launch_mode":"Train","parameters":"","iteration_count":1000,"learn_sets":["learn"],"name":"experiment"},
"iterations":[
{"learn":[56.14886547],"iteration":0,"passed_time":1.977747716,"remaining_time":1975.769968},
{"learn":[50.51019121],"iteration":1,"passed_time":4.179199188,"remaining_time":2085.420395},
{"learn":[45.49208556],"iteration":2,"passed_time":6.669136721,"remaining_time":2216.376437},
{"learn":[41.03034333],"iteration":3,"passed_time":9.570553824,"remaining_time":2383.067902,,
{"learn":[37.0376831],"iteration":4,"passed_time":11.77104039,"remaining_time":2342.437038,,
{"learn":[33.43582757],"iteration":5,"passed_time":14.06788985,"remaining_time":2330.58041,
{"learn":[30.2184222],"iteration":6,"passed_time":17.46599548,"remaining_time":2477.676216},
{"learn":[27.37635427],"iteration":7,"passed_time":20.14497764,"remaining_time":2497.977227},
{"learn":[24.80807828],"iteration":8,"passed_time":22.85457073,"remaining_time":2516.542177},
{"learn":[22.56251862],"iteration":9,"passed_time":24.01991511,"remaining_time":2377.971596},
{"learn":[20.54721184],"iteration":10,"passed_time":25.17610061,"remaining_time":2263.560319},
{"learn":[18.72964378],"iteration":11,"passed_time":26.73315621,"remaining_time":2201.029862},,
{"learn":[17.12360807],"iteration":12,"passed_time":27.54281536,"remaining_time":2091.13528,
,
{"learn":[15.66951273],"iteration":13,"passed_time":30.1501335,"remaining_time":2123.43083,
{"learn":[14.34776838],"iteration":14,"passed_time":34.15211755,"remaining_time":2242.655719},
{"learn":[13.22877962],"iteration":15,"passed_time":36.94590424,"remaining_time":2272.173111},
{"learn":[12.21427996],"iteration":16,"passed_time":39.28748917,"remaining_time":2271.741285},
{"learn":[11.29821916],"iteration":17,"passed_time":41.80932311,"remaining_time":2280.93085},
{"learn":[10.46872516],"iteration":18,"passed_time":43.87117476,"remaining_time":2265.138023},
{"learn":[9.763377216],"iteration":19,"passed_time":46.52918242,"remaining_time":2279.929939},
{"learn":[9.099113156],"iteration":20,"passed_time":48.12317416,"remaining_time":2243.456548},
{"learn":[8.541121037],"iteration":21,"passed_time":49.26017819,"remaining_time":2189.83883},
{"learn":[8.039012627],"iteration":22,"passed_time":50.44847363,"remaining_time":2142.963423},
{"learn":[7.591127674],"iteration":23,"passed_time":51.50398622,"remaining_time":2094.495439},
{"learn":[7.202686112],"iteration":24,"passed_time":53.07317412,"remaining_time":2069.853791},
{"learn":[6.864245394],"iteration":25,"passed_time":54.06649614,"remaining_time":2025.414125,,
{"learn":[6.565971829],"iteration":26,"passed_time":55.10902059,"remaining_time":1985.96581,
,
{"learn":[6.296984639],"iteration":27,"passed_time":56.12575076,"remaining_time":1948.36534,
,
{"learn":[6.07182532],"iteration":28,"passed_time":57.21965274,"remaining_time":1915.871821,,
{"learn":[5.868626895],"iteration":29,"passed_time":58.18886997,"remaining_time":1881.440129,,
{"learn":[5.694774999],"iteration":30,"passed_time":58.85216236,"remaining_time":1839.604688,,
{"learn":[5.543873945],"iteration":31,"passed_time":59.68462674,"remaining_time":1805.459959,,
{"learn":[5.398200184],"iteration":32,"passed_time":60.69880655,"remaining_time":1778.658968,,
{"learn":[5.284747651],"iteration":33,"passed_time":61.57972969,"remaining_time":1749.5887,
{,
{"learn":[5.180929955],"iteration":34,"passed_time":62.24539321,"remaining_time":1716.1944,
{,
{"learn":[5.078143326],"iteration":35,"passed_time":63.08188175,"remaining_time":1689.1926,
{,
{"learn":[4.996452155],"iteration":36,"passed_time":63.75880829,"remaining_time":1659.4522,
{,
{"learn":[4.914492778],"iteration":37,"passed_time":64.75369947,"remaining_time":1639.2910,
{,
{"learn":[4.849416534],"iteration":38,"passed_time":65.11853634,"remaining_time":1604.5875,
{,
{"learn":[4.788260465],"iteration":39,"passed_time":65.46561333,"remaining_time":1571.1747,
,
{"learn":[4.735934187],"iteration":40,"passed_time":65.88040876,"remaining_time":1540.95882,
,
{"learn":[4.679989325],"iteration":41,"passed_time":66.21575693,"remaining_time":1510.34988,
,
{"learn":[4.627380588],"iteration":42,"passed_time":66.6584929,"remaining_time":1483.539016,,
{"learn":[4.588531277],"iteration":43,"passed_time":66.98663866,"remaining_time":1455.436967,,
{"learn":[4.546231304],"iteration":44,"passed_time":67.31709755,"remaining_time":1428.618404,,
{"learn":[4.51468701],"iteration":45,"passed_time":67.72157683,"remaining_time":1404.486615,,
{"learn":[4.484984653],"iteration":46,"passed_time":68.10209056,"remaining_time":1380.87856},
{"learn":[4.44819097],"iteration":47,"passed_time":68.49301195,"remaining_time":1358.444737},
{"learn":[4.426323305],"iteration":48,"passed_time":68.84160844,"remaining_time":1336.089176},
{"le,
{"learn":[4.465399863],"iteration":49,"passed_time":69.40640901,"remaining_time":1318.7,
{"learn":[4.371750902],"iteration":50,"passed_time":69.59930101,"remaining_time":1295.092876,,
{"learn":[4.348266166],"iteration":51,"passed_time":70.13475424,"remaining_time":1278.61052},
{"learn":[4.323676043],"iteration":52,"passed_time":70.55181322,"remaining_time":1260.614474},
{"learn":[4.308221125],"iteration":53,"passed_time":70.89302465,"remaining_time":1241.940765},
{"learn":[4.292746292],"iteration":54,"passed_time":71.20759073,"remaining_time":1223.475877,,
{"learn":[4.270883331],"iteration":55,"passed_time":71.64533597,"remaining_time":1207.735663,,
{"learn":[4.250629541],"iteration":56,"passed_time":72.05318123,"remaining_time":1192.037718},
{"learn":[4.236253911],"iteration":57,"passed_time":72.42658293,"remaining_time":1176.30760,
,
{",
{"learn":[4.27567132],"iteration":58,"passed_time":73.12059413,"remaining_time":1166.2,
{,
,
{"learn":[4.261416919],"iteration":59,"passed_time":73.49327992,"remaining_time":1151.3,
{",
{"learn":[4.191866994],"iteration":60,"passed_time":73.62780805,"remaining_time":1133.385,
{",
{"learn":[4.179018504],"iteration":61,"passed_time":74.01795373,"remaining_time":1119.820,
{,
{,
{"learn":[4.220625792],"iteration":62,"passed_time":74.64830531,"remaining_time":1110.2,
{,
{"learn":[4.154105816],"iteration":63,"passed_time":74.77853056,"remaining_time":1093.636,
{",
{"learn":[4.141903758],"iteration":64,"passed_time":75.16380699,"remaining_time":1081.202,
{",
,
{"learn":[4.189174931],"iteration":65,"passed_time":75.78562758,"remaining_time":1072.4,
{",
{"learn":[4.119190057],"iteration":66,"passed_time":75.93889942,"remaining_time":1057.,
{"le,
,
{"learn":[4.166341264],"iteration":67,"passed_time":76.56865824,"remaining_time":1049,
{"le,
{"learn":[4.100019047],"iteration":68,"passed_time":76.73507304,"remaining_time":1035.3,
{"le,
{"learn":[4.082996833],"iteration":69,"passed_time":77.13419611,"remaining_time":1024.,
{"lea,
{"learn":[4.070718158],"iteration":70,"passed_time":77.6341875,"remaining_time":1015.8,
{"le,
{"learn":[4.06126581],"iteration":71,"passed_time":77.99062857,"remaining_time":1005.2,
{"le,
{"learn":[4.051731499],"iteration":72,"passed_time":78.30028053,"remaining_time":994.30,
{"le,
{"learn":[4.045238858],"iteration":73,"passed_time":78.62488369,"remaining_time":983.8,
{"learn":[4.080759055],"iteration":74,"passed_time":77.60406703,"remaining_time":957.1168268},
{"lea,
{"learn":[4.025886481],"iteration":75,"passed_time":79.28679883,"remaining_time":963.9,
{"learn,
{"learn":[4.078289735],"iteration":76,"passed_time":79.97390574,"remaining_time":958,
{"learn,
{"learn":[4.068593613],"iteration":77,"passed_time":80.2684576,"remaining_time":948,
{"learn,
{"learn":[4.057905449],"iteration":78,"passed_time":80.71291139,"remaining_time":940,
{"learn,
{"learn":[4.047109343],"iteration":79,"passed_time":81.01736822,"remaining_time":931,
{"lear,,
{"learn":[4.039977316],"iteration":80,"passed_time":81.44351542,"remaining_time":924,
{"learn,
{"learn":[4.033925411],"iteration":81,"passed_time":81.71602151,"remaining_time":914,
{"learn,
{"learn":[4.028795386],"iteration":82,"passed_time":81.9901253,"remaining_time":90,
{"learn",
{"learn":[4.023422321],"iteration":83,"passed_time":82.2062243,"remaining_time":896,
{"learn,
{"learn":[4.019242337],"iteration":84,"passed_time":82.43309197,"remaining_time":887,
{"lea,
{"learn":[4.009487427],"iteration":85,"passed_time":82.74450121,"remaining_time":879.,
{"lear,
{"learn":[3.998480167],"iteration":86,"passed_time":82.97447126,"remaining_time":870.,
{"lear,
{"learn":[3.991490309],"iteration":87,"passed_time":83.2726688,"remaining_time":863.0,
{"lea,
{"learn":[3.984362824],"iteration":88,"passed_time":83.50154119,"remaining_time":854.7,
{"lea,
{"learn":[3.976141959],"iteration":89,"passed_time":83.7526591,"remaining_time":846.83,
{"l,
{"learn":[3.968980711],"iteration":90,"passed_time":83.98864311,"remaining_time":838.963,
{",
{"learn":[3.961841681],"iteration":91,"passed_time":84.27347462,"remaining_time":831.7425,
{",
{"learn":[3.95418145],"iteration":92,"passed_time":84.57830192,"remaining_time":824.86580,
{,
{"learn":[3.95156804],"iteration":93,"passed_time":84.80392374,"remaining_time":817.365477,
,
{"learn":[3.947350922],"iteration":94,"passed_time":85.06021291,"remaining_time":810.310449,
,
{"learn":[3.93860742],"iteration":95,"passed_time":85.35765753,"remaining_time":803.7846084,,
{"learn":[3.932672863],"iteration":96,"passed_time":85.62559878,"remaining_time":797.112533,,
{"learn":[3.927484891],"iteration":97,"passed_time":85.85202731,"remaining_time":790.1890677,,
{"learn":[3.921977747],"iteration":98,"passed_time":86.11141281,"remaining_time":783.700837,
,
{"learn":[3.916390768],"iteration":99,"passed_time":86.38396815,"remaining_time":777.455713,
,
{"learn":[3.910914593],"iteration":100,"passed_time":86.65012375,"remaining_time":771.27189,
{,
{"learn":[3.907096112],"iteration":101,"passed_time":86.89321746,"remaining_time":765.00,
{"le,
{"learn":[3.903575156],"iteration":102,"passed_time":87.161078,"remaining_time":759.0629,
{",
{"learn":[3.899458409],"iteration":103,"passed_time":87.38898966,"remaining_time":752.8897,
{",
{"learn":[3.895552052],"iteration":104,"passed_time":87.60405363,"remaining_time":746.720,
{"l,
{"learn":[3.89136807],"iteration":105,"passed_time":87.86495501,"remaining_time":741.0497,
{",
{"learn":[3.885789603],"iteration":106,"passed_time":88.19011293,"remaining_time":736.0165,
,
{"learn":[3.88060886],"iteration":107,"passed_time":88.46302054,"remaining_time":730.6390215},
{"learn":[3.876286265],"iteration":108,"passed_time":88.73153093,"remaining_time":725.3192115},
{"learn":[3.873087012],"iteration":109,"passed_time":88.97052723,"remaining_time":719.8524476,,
{"learn":[3.868892112],"iteration":110,"passed_time":89.18070201,"remaining_time":714.24904,
{,
{"learn":[3.862475175],"iteration":111,"passed_time":89.48583393,"remaining_time":709.49,
{"le,
{"learn":[3.857547706],"iteration":112,"passed_time":89.74344852,"remaining_time":704.4463614},
{"learn":[3.854236145],"iteration":113,"passed_time":90.01548964,"remaining_time":699.5940686},
{"learn":[3.849980338],"iteration":114,"passed_time":90.29147679,"remaining_time":694.8517996},
{"learn":[3.846155661],"iteration":115,"passed_time":90.56601827,"remaining_time":690.1755185},
{"learn":[3.842123487],"iteration":116,"passed_time":90.80205832,"remaining_time":685.2,
{"lea,
{"learn":[3.838362654],"iteration":117,"passed_time":91.06095964,"remaining_time":680.6420881},
{"learn":[3.834597207],"iteration":118,"passed_time":91.37329475,"remaining_time":676.4695183},
{"learn":[3.830814048],"iteration":119,"passed_time":91.65549765,"remaining_time":672.1403161},
{"learn":[3.828007518],"iteration":120,"passed_time":91.90945028,"remaining_time":667.6727834},
{"learn":[3.824567822],"iteration":121,"passed_time":92.17603452,"remaining_time":663.365232},
{"learn":[3.821725382],"iteration":122,"passed_time":92.45997332,"remaining_time":659.2471269},
{"learn":[3.820020218],"iteration":123,"passed_time":92.66726492,"remaining_time":654.6493877},
{"learn":[3.817227166],"iteration":124,"passed_time":92.91019414,"remaining_time":650.371359},
{"learn":[3.813933755],"iteration":125,"passed_time":93.19026845,"remaining_time":646.4150367},
{"learn":[3.810080535],"iteration":126,"passed_time":93.49576493,"remaining_time":642.6,
{"lea,
{"learn":[3.805774903],"iteration":127,"passed_time":93.71856444,"remaining_time":638.,
{"lear,
{"learn":[3.802156768],"iteration":128,"passed_time":93.97321341,"remaining_time":634.,
{"lear,
{"learn":[3.798158718],"iteration":129,"passed_time":94.26111742,"remaining_time":630,
{"learn,
{"learn":[3.794952789],"iteration":130,"passed_time":94.56764759,"remaining_time":627,
{"lear,
{"learn":[3.791821594],"iteration":131,"passed_time":94.8132163,"remaining_time":623.4,
{"lea,
{"learn":[3.7879224],"iteration":132,"passed_time":95.09194197,"remaining_time":619.885,
{"l,
{"learn":[3.78445927],"iteration":133,"passed_time":95.3652263,"remaining_time":616.31556,
,
{"learn":[3.781992578],"iteration":134,"passed_time":95.62453044,"remaining_time":612.705324,
,
{"learn":[3.779257646],"iteration":135,"passed_time":95.85206032,"remaining_time":608.94250,
{,
{"learn":[3.776257842],"iteration":136,"passed_time":96.14767862,"remaining_time":605.6601,
{",
{"learn":[3.773722556],"iteration":137,"passed_time":96.32986895,"remaining_time":601.7126,
{",
{"learn":[3.770997497],"iteration":138,"passed_time":96.64013638,"remaining_time":598.612,
{"l,
{"learn":[3.768342373],"iteration":139,"passed_time":96.91032876,"remaining_time":595.306,
{"l,
{"learn":[3.766343344],"iteration":140,"passed_time":97.15285117,"remaining_time":591.874,
{"l,
{"learn",
{"learn":[3.724480582],"iteration":141,"passed_time":97.15614857,"remaining_tim,
{"l,
{"learn",
{"learn":[3.721409257],"iteration":142,"passed_time":97.46373794,"remaining_tim,
{"l,
{"learn,
{"learn":[3.718809725],"iteration":143,"passed_time":97.72724264,"remaining_time,
{"l,
{"learn,
{"learn":[3.717449242],"iteration":144,"passed_time":97.94192584,"remaining_time,
{"learn":[3.,
{"learn":[3.715635665],"iteration":145,"passed_time":98.23047744,"remaining_time,
{"l,
{"learn,
{"learn":[3.713336959],"iteration":146,"passed_time":98.51133887,"remaining_time,
{"l,
{"learn,
{"learn":[3.710032492],"iteration":147,"passed_time":98.76029426,"remaining_tim,
{"learn":[3.7,
{"learn":[3.708186412],"iteration":148,"passed_time":99.05597873,"remaining_tim,
{"learn":[3.7,
{"learn":[3.706674389],"iteration":149,"passed_time":99.27830652,"remaining_tim,
{"learn":[3.7,
{"learn":[3.703679252],"iteration":150,"passed_time":99.64015551,"remaining_ti,
{"learn":[3.7,
{"learn":[3.701174576],"iteration":151,"passed_time":99.92936111,"remaining_tim,
{"learn":[3.7,
{"learn":[3.699626483],"iteration":152,"passed_time":100.183197,"remaining_time,
{"learn":[3.,
{"learn":[3.696907626],"iteration":153,"passed_time":100.4704298,"remaining_time,
{"learn":[3.,
{"learn":[3.693968245],"iteration":154,"passed_time":100.749354,"remaining_tim,
{"learn":[3.7,
{"learn":[3.691900658],"iteration":155,"passed_time":101.3232199,"remaining_ti,
{"le,
{"lea,
{"learn":[3.690553141],"iteration":156,"passed_time":101.6821359,"remaining_time",
{"le,
{"lea,
{"learn":[3.688426904],"iteration":157,"passed_time":102.0761791,"remaining_time",
{",
{"learn,
{"learn":[3.686774749],"iteration":158,"passed_time":102.4046963,"remaining_time,
{"learn":[3.,
{"learn":[3.685248804],"iteration":159,"passed_time":102.5658312,"remaining_time,
{"learn":[3.,
{"learn":[3.683495314],"iteration":160,"passed_time":102.8075912,"remaining_time,
{"learn":[3,
{"learn":[3.68197399],"iteration":161,"passed_time":103.0336812,"remaining_time":,
{"learn":[3.708009339],"iteration":162,"passed_time":102.0071407,"remaining_time":523.8035382},
{"learn":[3.705297635],"iteration":163,"passed_time":102.3041015,"remaining_time":521.5013955},
{"learn":[3.703096662],"iteration":164,"passed_time":102.5980054,"remaining_time":519.208088},
{"learn":[3.701662467],"iteration":165,"passed_time":102.8503907,"remaining_time":516.730276},
{"l,
{"learn":[3.706797848],"iteration":166,"passed_time":104.636669,"remaining_time":521.9302,
{",
{"le,
{"learn":[3.669681737],"iteration":167,"passed_time":104.680452,"remaining_time":518,
{",
{"learn":[3.702579557],"iteration":168,"passed_time":105.1554895,"remaining_time":517.0663,
{",
{"l,
{"learn":[3.66561676],"iteration":169,"passed_time":105.2669592,"remaining_time":513,
{",
{"l,
{"learn":[3.663797423],"iteration":170,"passed_time":105.465108,"remaining_time":511.,
{",
{"learn":[3.696957148],"iteration":171,"passed_time":106.0449049,"remaining_time":510.495,
{"l,
{"learn":[3.695165802],"iteration":172,"passed_time":106.319586,"remaining_time":508.2444,
{,
{"learn":[3.693500436],"iteration":173,"passed_time":106.579039,"remaining_time":505.944173,
,
{"l,
{"learn":[3.656221798],"iteration":174,"passed_time":106.6209304,"remaining_time":502.6,,
{"learn":[3.688877002],"iteration":175,"passed_time":107.0964042,"remaining_time":501.4058923,,
{"learn":[3.687495816],"iteration":176,"passed_time":107.3574573,"remaining_time":499.1818493,
{"lea,
{"learn":[3.651075354],"iteration":177,"passed_time":107.4227707,"remaining_time":496.0,
{"lea,
{"learn":[3.649321339],"iteration":178,"passed_time":107.9278464,"remaining_time":495.,,
{"learn":[3.675827707],"iteration":179,"passed_time":106.9291055,"remaining_time":487.1214806,,
{"learn":[3.674081138],"iteration":180,"passed_time":107.2248066,"remaining_time":485.1774396,,
{"lea,
{"learn":[3.645075454],"iteration":181,"passed_time":108.8524018,"remaining_time":489.,,
{"lea,
{"learn":[3.64350292],"iteration":182,"passed_time":109.161755,"remaining_time":487.35,,
{"l,
{"learn":[3.642038223],"iteration":183,"passed_time":109.4963917,"remaining_time":485.5,
,
{"l,
{"learn":[3.641260296],"iteration":184,"passed_time":109.6899107,"remaining_time":483.2,
{"lea,
{"learn":[3.640300334],"iteration":185,"passed_time":109.9650826,"remaining_time":481.2,
{"learn":[3.667787845],"iteration":186,"passed_time":110.4572982,"remaining_time":480.2234409},
{"learn":[3.666009693],"iteration":187,"passed_time":110.6963478,"remaining_time":478.1140127},
{"le,
{"learn":[3.63578483],"iteration":188,"passed_time":110.7369886,"remaining_time":475.173,
{"l,
{"learn":[3.634250035],"iteration":189,"passed_time":111.034408,"remaining_time":473.357,
{"learn":[3.655247045],"iteration":190,"passed_time":109.9847861,"remaining_time":465.8517903},
{"learn":[3.653651877],"iteration":191,"passed_time":110.3430935,"remaining_time":464.3605186},
{"learn":[3.652135558],"iteration":192,"passed_time":110.6821207,"remaining_time":462.8003698},
{"learn":[3.650024525],"iteration":193,"passed_time":110.9250696,"remaining_time":460.8536395},
{",
{"learn":[3.627858967],"iteration":194,"passed_time":112.4929091,"remaining_time":464.3938,
{"learn":[3.647232659],"iteration":195,"passed_time":111.4801583,"remaining_time":457.2961594},
{"learn":[3.645916301],"iteration":196,"passed_time":111.7335938,"remaining_time":455.4420093},
{"learn":[3.644618679],"iteration":197,"passed_time":112.0165353,"remaining_time":453.7235419},
{",
{"learn":[3.621914107],"iteration":198,"passed_time":113.5450571,"remaining_time":457.0331,
{",
{"learn":[3.62067685],"iteration":199,"passed_time":113.7703516,"remaining_time":455.08140,
{,
{"learn":[3.619406412],"iteration":200,"passed_time":114.0465069,"remaining_time":453.34905,,
{"learn":[3.618265358],"iteration":201,"passed_time":114.2899353,"remaining_time":451.50182,
{,
{"learn":[3.616673491],"iteration":202,"passed_time":114.5420689,"remaining_time":449.70457,
,,
{"learn":[3.615487215],"iteration":203,"passed_time":114.824538,"remaining_time":448.040844,
,
{"learn":[3.639197539],"iteration":204,"passed_time":115.3325746,"remaining_time":447.265350,
,
{"learn":[3.637129504],"iteration":205,"passed_time":115.6471378,"remaining_time":445.7467,
{",
{"learn":[3.636004335],"iteration":206,"passed_time":115.8679365,"remaining_time":443.8805,
{",
{"learn":[3.634984488],"iteration":207,"passed_time":116.1133797,"remaining_time":442.124,
{,
,
{"learn":[3.633759006],"iteration":208,"passed_time":116.4040551,"remaining_time":440.55,
{,
{,
{"learn":[3.631784978],"iteration":209,"passed_time":116.7596295,"remaining_time":439.23,
,
{",
{"learn":[3.629675407],"iteration":210,"passed_time":117.0501994,"remaining_time":437.69,
,
{",
{"learn":[3.627892412],"iteration":211,"passed_time":117.3179249,"remaining_time":436.06,,
{"l,
{"learn":[3.626643261],"iteration":212,"passed_time":117.5749435,"remaining_time":434.42,,
{"l,
{"learn":[3.625366779],"iteration":213,"passed_time":117.8175661,"remaining_time":432.73,,
{"l,
{"learn":[3.623545685],"iteration":214,"passed_time":118.0681109,"remaining_time":431.08,,
{"learn":[3.599624716],"iteration":215,"passed_time":118.0758332,"remaining_time":428.5715426,
{"le,
{"learn":[3.621136692],"iteration":216,"passed_time":118.5480529,"remaining_time":427.75,
{"le,
{"learn":[3.619403758],"iteration":217,"passed_time":118.8364841,"remaining_time":426.28,,
{"l,
{"learn":[3.617901997],"iteration":218,"passed_time":119.096076,"remaining_time":424.721,,
{",
{"learn":[3.616692673],"iteration":219,"passed_time":119.3601707,"remaining_time":423.186,,
{",
{"learn":[3.615585927],"iteration":220,"passed_time":119.6734756,"remaining_time":421.83,
,
{",
{"learn":[3.613982931],"iteration":221,"passed_time":119.9437944,"remaining_time":420.34,
{"le,
{"learn":[3.612700603],"iteration":222,"passed_time":120.2320008,"remaining_time":418.9,
{"lea,
{"learn":[3.611640309],"iteration":223,"passed_time":120.4837761,"remaining_time":417.3,
{"lea,
{"learn":[3.61052773],"iteration":224,"passed_time":120.7573918,"remaining_time":415.9421271},
{"learn":[3.609181336],"iteration":225,"passed_time":121.0304243,"remaining_time":414.,
{"lear,
{"learn":[3.608256605],"iteration":226,"passed_time":121.301674,"remaining_time":413.0,
{"le,
{"learn":[3.606497627],"iteration":227,"passed_time":121.5855041,"remaining_time":411.68,
{"le,
{"learn":[3.605502804],"iteration":228,"passed_time":121.8296806,"remaining_time":410.1,
{"lea,
{"learn":[3.604435464],"iteration":229,"passed_time":122.1300202,"remaining_time":408.8,
{"lea,
{"learn":[3.603792097],"iteration":230,"passed_time":122.3200186,"remaining_time":407.2,
{"lea,
{"learn":[3.602426954],"iteration":231,"passed_time":122.6019838,"remaining_time":40,
{"learn",
{"learn":[3.601365297],"iteration":232,"passed_time":122.9095927,"remaining_time":404.599389},
{"learn":[3.600412414],"iteration":233,"passed_time":123.1760497,"remaining_time":403.217325},
{"learn":[3.599306107],"iteration":234,"passed_time":123.4458863,"remaining_time":401.8557574},
{"learn":[3.597689914],"iteration":235,"passed_time":123.696957,"remaining_time":400.4426912},
{"learn":[3.596359902],"iteration":236,"passed_time":123.9800149,"remaining_time":399.1424109},
{"learn":[3.595354231],"iteration":237,"passed_time":124.2849317,"remaining_time":397.9206636},
{"learn":[3.594571527],"iteration":238,"passed_time":124.5105307,"remaining_time":39,
{"learn",
{"learn":[3.59342979],"iteration":239,"passed_time":124.741097,"remaining_time":395,
{"learn,
{"learn":[3.592055582],"iteration":240,"passed_time":124.980171,"remaining_time":393.,
{"lear,
{"learn":[3.591025831],"iteration":241,"passed_time":125.2186436,"remaining_time":392,
{"lear,
{"learn":[3.58915067],"iteration":242,"passed_time":125.5119669,"remaining_time":390.9,
{"lea,
{"learn":[3.588237495],"iteration":243,"passed_time":125.7769157,"remaining_time":389.7,
{"lea,
{"learn":[3.586627149],"iteration":244,"passed_time":126.0897154,"remaining_time":388.5,
{"lea,
{"learn":[3.585653202],"iteration":245,"passed_time":126.3392394,"remaining_time":387.2,
{"lea,
{"learn":[3.584222584],"iteration":246,"passed_time":126.6335153,"remaining_time":386.0527815},
{"learn":[3.583383824],"iteration":247,"passed_time":126.9231168,"remaining_time":384.8636444},
{"learn":[3.582572966],"iteration":248,"passed_time":127.1644379,"remaining_time":38,
{"learn",
{"learn":[3.581602198],"iteration":249,"passed_time":127.409511,"remaining_time":382,
{"lear,
{"learn":[3.58088479],"iteration":250,"passed_time":127.661361,"remaining_time":380.94,
{"l,
{"learn":[3.579316606],"iteration":251,"passed_time":127.930613,"remaining_time":379.7305,
{",
{"learn":[3.578009392],"iteration":252,"passed_time":128.2250674,"remaining_time":378.5933,
{",
{"learn":[3.57700239],"iteration":253,"passed_time":128.4769863,"remaining_time":377.33792,
{,
{"learn":[3.575670917],"iteration":254,"passed_time":128.6919296,"remaining_time":375.98230,
{,
{"learn":[3.574998135],"iteration":255,"passed_time":128.963017,"remaining_time":374.798,
{"l,
{"learn":[3.57398649],"iteration":256,"passed_time":129.1869847,"remaining_time":373.4861,
{",
{"learn":[3.5727517],"iteration":257,"passed_time":129.5270995,"remaining_time":372.515921,
,
{"learn":[3.571763672],"iteration":258,"passed_time":129.7556347,"remaining_time":371.231371,
,
{"learn":[3.570332962],"iteration":259,"passed_time":129.9591867,"remaining_time":369.883839,,
{"learn":[3.569385275],"iteration":260,"passed_time":130.2430398,"remaining_time":368.7724383,,
{"learn":[3.56834929],"iteration":261,"passed_time":130.4874237,"remaining_time":367.5561782},
{"learn":[3.567743157],"iteration":262,"passed_time":130.7039586,"remaining_time":366.2692681},
{"learn":[3.567070251],"iteration":263,"passed_time":130.9152573,"remaining_time":364.9758689},
{"learn":[3.565918913],"iteration":264,"passed_time":131.1319951,"remaining_time":363.7057222},
{"learn":[3.56517397],"iteration":265,"passed_time":131.3939034,"remaining_time":362.5681395},
{"learn":[3.564079604],"iteration":266,"passed_time":131.6758408,"remaining_time":361.4921024,,
{"learn":[3.563162306],"iteration":267,"passed_time":131.9418758,"remaining_time":360.3785564,,
{"learn":[3.562030957],"iteration":268,"passed_time":132.1880039,"remaining_time":359.217215,
,
{"learn":[3.561366292],"iteration":269,"passed_time":132.478966,"remaining_time":358.18387,
{"learn":[3.559167002],"iteration":270,"passed_time":131.3620885,"remaining_time":353.3688653},
{"learn":[3.558522012],"iteration":271,"passed_time":131.6700792,"remaining_time":352.4110943},
{"learn":[3.557439912],"iteration":272,"passed_time":131.9950284,"remaining_time":351.5032442},
{"learn":[3.556470292],"iteration":273,"passed_time":132.2949649,"remaining_time":350.5333741},
{"learn":[3.555568407],"iteration":274,"passed_time":132.5551529,"remaining_time":349.4635848},
{"learn":[3.555163443],"iteration":275,"passed_time":132.7889131,"remaining_time":348.3303373},
,
{"learn":[3.554946827],"iteration":276,"passed_time":134.5731673,"remaining_time":351.250541,
,
{"learn":[3.554277109],"iteration":277,"passed_time":134.8770925,"remaining_time":350.292304,
,
{"learn":[3.553195064],"iteration":278,"passed_time":135.1400958,"remaining_time":349.233007,
,
{"learn":[3.552613201],"iteration":279,"passed_time":135.3755019,"remaining_time":348.10843,
{,
,
{"learn":[3.537386006],"iteration":280,"passed_time":135.4051885,"remaining_time":346.463,
{,
{"learn":[3.550950837],"iteration":281,"passed_time":135.9450078,"remaining_time":346.12948,
{,
{"learn":[3.550170946],"iteration":282,"passed_time":136.2345528,"remaining_time":345.15962,
{,
{"learn":[3.549301674],"iteration":283,"passed_time":136.4765856,"remaining_time":344.07477,
{,
{"learn":[3.548675102],"iteration":284,"passed_time":136.6757418,"remaining_time":342.88826,
{,
{"learn":[3.547712723],"iteration":285,"passed_time":136.9704128,"remaining_time":341.94711,
{,
{"learn":[3.547161723],"iteration":286,"passed_time":137.1972749,"remaining_time":340.84201,
{,
{"learn":[3.5465224],"iteration":287,"passed_time":137.4332072,"remaining_time":339.7654289,,
{"learn":[3.545885952],"iteration":288,"passed_time":137.6658716,"remaining_time":338.686625,
,
{"learn":[3.545075715],"iteration":289,"passed_time":137.878864,"remaining_time":337.5654947,,
{"learn":[3.54479618],"iteration":290,"passed_time":138.128367,"remaining_time":336.5395608},
{"learn":[3.544127102],"iteration":291,"passed_time":138.3991352,"remaining_time":335.5705058},
{"learn":[3.543073218],"iteration":292,"passed_time":138.6472263,"remaining_time":334.5514983},
{"learn":[3.542411116],"iteration":293,"passed_time":138.9229501,"remaining_time":333.6040911},
{"learn":[3.541833931],"iteration":294,"passed_time":139.1573911,"remaining_time":332.5625786},
{"learn":[3.540589606],"iteration":295,"passed_time":139.4540503,"remaining_time":331.6744979},
{"learn":[3.539789349],"iteration":296,"passed_time":139.7217454,"remaining_time":330.7218418,,
{"learn":[3.53929934],"iteration":297,"passed_time":139.9574849,"remaining_time":329.6985047},
{"learn":[3.538218023],"iteration":298,"passed_time":140.2193281,"remaining_time":328.7416353},
{"learn":[3.537329948],"iteration":299,"passed_time":140.5167465,"remaining_time":327.8724085},
{"learn":[3.536570488],"iteration":300,"passed_time":140.7635556,"remaining_time":326.8894531},
{"learn":[3.535059762],"iteration":301,"passed_time":140.9944706,"remaining_time":325.8746373},
{"learn":[3.534316399],"iteration":302,"passed_time":141.2867043,"remaining_time":325.0060491},
{"learn":[3.53320697],"iteration":303,"passed_time":141.559999,"remaining_time":324.0978924},
{"learn":[3.532350121],"iteration":304,"passed_time":141.8367142,"remaining_time":323.2016929},
{"learn":[3.531636076],"iteration":305,"passed_time":142.0950102,"remaining_time":322.2677683},
{"learn":[3.530870514],"iteration":306,"passed_time":142.4178651,"remaining_time":321.4839756},
{"learn":[3.529907827],"iteration":307,"passed_time":142.6327215,"remaining_time":320.46053},
{"learn":[3.529389063],"iteration":308,"passed_time":142.8525583,"remaining_time":319.4534556},
{"learn":[3.528605674],"iteration":309,"passed_time":143.0958022,"remaining_time":318.5035597},
{"learn":[3.527610336],"iteration":310,"passed_time":143.3760881,"remaining_time":317.6402723},
{"learn":[3.526761658],"iteration":311,"passed_time":143.6009151,"remaining_time":316.6584281},
{"learn":[3.525878705],"iteration":312,"passed_time":143.8585314,"remaining_time":315.7533901},
{"learn":[3.525115695],"iteration":313,"passed_time":144.1417999,"remaining_time":314.9085183},
{"learn":[3.524224958],"iteration":314,"passed_time":144.3636727,"remaining_time":313.933701},
{,
{"learn":[3.51295453],"iteration":315,"passed_time":144.4113982,"remaining_time":312.58669,
{,
{"learn":[3.512237877],"iteration":316,"passed_time":144.7384535,"remaining_time":311.84972,
,
{"learn":[3.511686815],"iteration":317,"passed_time":144.95713,"remaining_time":310.8829014},
{"learn":[3.510956204],"iteration":318,"passed_time":145.2626278,"remaining_time":310.1061114},
{"learn":[3.520222045],"iteration":319,"passed_time":145.7649023,"remaining_time":309.7504174},,
{"learn":[3.518368715],"iteration":320,"passed_time":144.4977144,"remaining_time":305.65092,
{,
{"learn":[3.517781921],"iteration":321,"passed_time":144.7433027,"remaining_time":304.77005,
{"learn":[3.508531473],"iteration":322,"passed_time":146.2749422,"remaining_time":306.588656},
{"learn":[3.507750949],"iteration":323,"passed_time":146.5306947,"remaining_time":305.7245359},
{"learn":[3.506842009],"iteration":324,"passed_time":146.8297364,"remaining_time":304.9540678},
{"learn":[3.506034477],"iteration":325,"passed_time":147.1471963,"remaining_time":304.2245715},
{"learn":[3.505288373],"iteration":326,"passed_time":147.3978765,"remaining_time":303.3601555},
{"learn":[3.504720341],"iteration":327,"passed_time":147.6509785,"remaining_time":302.5044438,,
{"learn":[3.503806662],"iteration":328,"passed_time":147.9327935,"remaining_time":301.7109558,,
{"learn":[3.502977754],"iteration":329,"passed_time":148.205209,"remaining_time":300.901485},
{"learn":[3.50233327],"iteration":330,"passed_time":148.4947621,"remaining_time":300.1298969},
{"learn":[3.501785998],"iteration":331,"passed_time":148.7233206,"remaining_time":299.2384884},
{"learn":[3.501289487],"iteration":332,"passed_time":148.9854141,"remaining_time":298.4182319},
{"learn":[3.500456946],"iteration":333,"passed_time":149.3387189,"remaining_time":297.783194},
{"learn":[3.500105656],"iteration":334,"passed_time":149.5855694,"remaining_time":296.9385184},
{"learn":[3.49959909],"iteration":335,"passed_time":149.8298078,"remaining_time":296.0922392},
{"learn":[3.498958545],"iteration":336,"passed_time":150.1109152,"remaining_time":295.3220677},
{"learn":[3.498655521],"iteration":337,"passed_time":150.3583703,"remaining_time":294.488879},
{"learn":[3.49818421],"iteration":338,"passed_time":150.6111623,"remaining_time":293.6695525},
{"learn":[3.49756412],"iteration":339,"passed_time":150.8580711,"remaining_time":292.842138},
{"learn":[3.497081662],"iteration":340,"passed_time":151.0835038,"remaining_time":291.9766247},
{"learn":[3.496533075],"iteration":341,"passed_time":151.2865945,"remaining_time":291.0718689},
{"learn":[3.496012352],"iteration":342,"passed_time":151.5329827,"remaining_time":290.2541389},
{"learn":[3.495393884],"iteration":343,"passed_time":151.7761236,"remaining_time":289.4335379},
{"learn":[3.49479026],"iteration":344,"passed_time":152.0272348,"remaining_time":288.6314168},
{"learn":[3.494260624],"iteration":345,"passed_time":152.2476029,"remaining_time":287.7743709},
{"learn":[3.493837775],"iteration":346,"passed_time":152.5098232,"remaining_time":286.9997537},
{"learn":[3.493286412],"iteration":347,"passed_time":152.7710648,"remaining_time":286.2262478},
{"learn":[3.492714091],"iteration":348,"passed_time":153.0466837,"remaining_time":285.4824959},
{"learn":[3.491947098],"iteration":349,"passed_time":153.3205279,"remaining_time":284.7381233},
{"learn":[3.491428348],"iteration":350,"passed_time":153.5877731,"remaining_time":283.9842301},
{"learn":[3.490980025],"iteration":351,"passed_time":153.8532474,"remaining_time":283.2298419},
{"learn":[3.490504377],"iteration":352,"passed_time":154.108249,"remaining_time":282.4590286},
{"learn":[3.489771612],"iteration":353,"passed_time":154.4012371,"remaining_time":281.7604496},
{"learn":[3.48903938],"iteration":354,"passed_time":154.6804711,"remaining_time":281.0391658},
{"learn":[3.488330942],"iteration":355,"passed_time":154.8738205,"remaining_time":280.1650012},
{"learn":[3.495103644],"iteration":356,"passed_time":153.7876161,"remaining_time":276.9900201,
{"learn":[3.486793109],"iteration":357,"passed_time":155.3717304,"remaining_time":278.6275166},,
{"learn":[3.493666914],"iteration":358,"passed_time":154.2822466,"remaining_time":275.473315,,
{"learn":[3.493146967],"iteration":359,"passed_time":154.5149804,"remaining_time":274.6932985,
{"learn":[3.485061893],"iteration":360,"passed_time":156.0733187,"remaining_time":276.2627442},
{"learn":[3.492191893],"iteration":361,"passed_time":155.0214584,"remaining_time":273.2146145},
{"learn":[3.491297987],"iteration":362,"passed_time":155.2868373,"remaining_time":272.5005932},
{"learn":[3.490701047],"iteration":363,"passed_time":155.5467791,"remaining_time":271.7795371,
{"learn":[3.48256288],"iteration":364,"passed_time":157.1242692,"remaining_time":273.3531806},
,
{"learn":[3.490018896],"iteration":365,"passed_time":156.059765,"remaining_time":270.333035,,
{"learn":[3.481382796],"iteration":366,"passed_time":157.5969199,"remaining_time":271.82248,
{,,
{"learn":[3.489041389],"iteration":367,"passed_time":156.5499882,"remaining_time":268.8575,,
{,
{"learn":[3.488645865],"iteration":368,"passed_time":156.8118663,"remaining_time":268.1525,,
{,
{"learn":[3.488162091],"iteration":369,"passed_time":157.058475,"remaining_time":267.42388,
{,
{"learn":[3.48772005],"iteration":370,"passed_time":157.3089283,"remaining_time":266.704355,
,
{"learn":[3.48736588],"iteration":371,"passed_time":157.5485951,"remaining_time":265.9691336,,
{"learn":[3.486730741],"iteration":372,"passed_time":157.8042309,"remaining_time":265.2634122,,
{"learn":[3.486233975],"iteration":373,"passed_time":158.0545983,"remaining_time":264.551279,
,
{"learn":[3.485653316],"iteration":374,"passed_time":158.301064,"remaining_time":263.8351067,,
{"learn":[3.48507114],"iteration":375,"passed_time":158.5473378,"remaining_time":263.1211138},
{"learn":[3.484607882],"iteration":376,"passed_time":158.783128,"remaining_time":262.3922778},
{"learn":[3.484174702],"iteration":377,"passed_time":159.0348944,"remaining_time":261.692339,,,
{"learn":[3.483736929],"iteration":378,"passed_time":159.3130586,"remaining_time":261.0380195,,
{"learn":[3.482985965],"iteration":379,"passed_time":159.5802209,"remaining_time":260.3677288,,
{"learn":[3.482380537],"iteration":380,"passed_time":159.9565493,"remaining_time":259.8769134,,
{"learn":[3.481795204],"iteration":381,"passed_time":160.2197258,"remaining_time":259.203640,
,
{"learn":[3.481346036],"iteration":382,"passed_time":160.4255234,"remaining_time":258.440072,
,
{"learn":[3.480805961],"iteration":383,"passed_time":160.6559827,"remaining_time":257.7189,
{",
{"learn":[3.480426447],"iteration":384,"passed_time":160.9220689,"remaining_time":257.0573,
{",
{"learn":[3.479639079],"iteration":385,"passed_time":161.1516575,"remaining_time":256.339,
{"l,
{"learn":[3.479329927],"iteration":386,"passed_time":161.3824274,"remaining_time":255.626,
{"l,
{"learn":[3.478977916],"iteration":387,"passed_time":161.6332078,"remaining_time":254.947,
{"l,
{"learn":[3.478368275],"iteration":388,"passed_time":161.8792357,"remaining_time":254.262,
{"l,
{"learn":[3.477928448],"iteration":389,"passed_time":162.2955272,"remaining_time":253.846,
{"l,
{"learn":[3.477417119],"iteration":390,"passed_time":162.5805601,"remaining_time":253.226,
{"l,
{"learn":[3.47700007],"iteration":391,"passed_time":162.8709694,"remaining_time":252.6161,
{",
{"learn":[3.476499245],"iteration":392,"passed_time":163.1618066,"remaining_time":252.0081,
{",
{"learn":[3.475995019],"iteration":393,"passed_time":163.4944578,"remaining_time":251.4660,
{,
{"learn":[3.475678606],"iteration":394,"passed_time":163.6992964,"remaining_time":250.72930,
{,
{"learn":[3.47519517],"iteration":395,"passed_time":163.9838842,"remaining_time":250.116833,
,
{"learn":[3.474661261],"iteration":396,"passed_time":164.1978673,"remaining_time":249.398775,
,
{"learn":[3.474110161],"iteration":397,"passed_time":164.4508086,"remaining_time":248.74217,
{,
{"learn":[3.473502587],"iteration":398,"passed_time":164.7272977,"remaining_time":248.12307,
{,
{"learn":[3.473021838],"iteration":399,"passed_time":164.9770075,"remaining_time":247.46551,
{,
{"learn":[3.472280758],"iteration":400,"passed_time":165.2540072,"remaining_time":246.85074,
{,
{"learn":[3.47198538],"iteration":401,"passed_time":165.4509657,"remaining_time":246.118,
{"l,
{"learn":[3.471345711],"iteration":402,"passed_time":165.7415856,"remaining_time":245.527,
{"l,
{"learn":[3.470930626],"iteration":403,"passed_time":165.9711379,"remaining_time":244.848,
{"l,
{"learn":[3.470571783],"iteration":404,"passed_time":166.3009171,"remaining_time":244,
{"learn,
{"learn":[3.469921343],"iteration":405,"passed_time":166.5453416,"remaining_time":243,
{"learn,
{"learn":[3.469178921],"iteration":406,"passed_time":166.8135925,"remaining_time":243,
{"learn,
{"learn":[3.468900132],"iteration":407,"passed_time":167.0751641,"remaining_time":242,
{"learn,
{"learn":[3.468644826],"iteration":408,"passed_time":167.2904673,"remaining_time":24,
{"learn",
{"learn":[3.467954635],"iteration":409,"passed_time":167.5762733,"remaining_time":24,
{"learn",
{"learn":[3.467540988],"iteration":410,"passed_time":167.873288,"remaining_time":24,
{"learn",
{"learn":[3.466963254],"iteration":411,"passed_time":168.1391883,"remaining_time":23,
{"learn",
{"learn":[3.466536761],"iteration":412,"passed_time":168.3929051,"remaining_time":23,
{"learn",
{"learn":[3.466115751],"iteration":413,"passed_time":168.6199442,"remaining_time":2,
{"learn",
{"learn":[3.4653692],"iteration":414,"passed_time":168.887484,"remaining_time":238.0,
{"lea,
{"learn":[3.464997818],"iteration":415,"passed_time":169.1381895,"remaining_time":237.4,
{"lea,
{"learn":[3.464715239],"iteration":416,"passed_time":169.3681542,"remaining_time":236.7,
{"le,
{"learn":[3.464133163],"iteration":417,"passed_time":169.5809582,"remaining_time":236.11,
{"le,
{"learn":[3.463798883],"iteration":418,"passed_time":169.7857332,"remaining_time":235.43,
{"le,
{"learn":[3.463289972],"iteration":419,"passed_time":170.0278026,"remaining_time":234.80,
{"le,
{"learn":[3.462915608],"iteration":420,"passed_time":170.2644554,"remaining_time":234.16,
{"le,
{"learn":[3.462570928],"iteration":421,"passed_time":170.5178442,"remaining_time":233.55,
{"le,
{"learn":[3.461996005],"iteration":422,"passed_time":170.79815,"remaining_time":232.979,
{"l,
{"learn":[3.461494337],"iteration":423,"passed_time":171.0373678,"remaining_time":232.352,
{"l,
{"learn":[3.460820218],"iteration":424,"passed_time":171.3389442,"remaining_time":231.811,
{"l,
{"learn":[3.460296307],"iteration":425,"passed_time":171.6343518,"remaining_time":231.263,
{"l,
{"learn":[3.459912365],"iteration":426,"passed_time":171.9523421,"remaining_time":230.746,
{"learn":[3.453435961],"iteration":427,"passed_time":173.4930869,"remaining_time":231.8645927},
{"l,
{"learn":[3.458690973],"iteration":428,"passed_time":172.4752858,"remaining_time":229.565,
{"l,
{"learn":[3.458214444],"iteration":429,"passed_time":172.708379,"remaining_time":228.9390,
{,
{"learn":[3.457922054],"iteration":430,"passed_time":172.9684249,"remaining_time":228.35042,
{,
{"learn":[3.457306473],"iteration":431,"passed_time":173.3104024,"remaining_time":227.87108,
{,
{"learn":[3.456953769],"iteration":432,"passed_time":173.6301424,"remaining_time":227.36325,
{,
{"learn":[3.4561541],"iteration":433,"passed_time":173.9000487,"remaining_time":226.7913078,,
{"learn":[3.455520463],"iteration":434,"passed_time":174.1496495,"remaining_time":226.1943723,,
{"learn":[3.454958334],"iteration":435,"passed_time":174.3704137,"remaining_time":225.5617278,,
{"learn":[3.454593683],"iteration":436,"passed_time":174.6573044,"remaining_time":225.0161611},
{"learn":[3.45399469],"iteration":437,"passed_time":174.9034887,"remaining_time":224.4195449},
{"learn":[3.45383931],"iteration":438,"passed_time":175.1034951,"remaining_time":223.76551,
{,
{"learn":[3.453013832],"iteration":439,"passed_time":175.4387054,"remaining_time":223.2856251},
{"learn":[3.452561216],"iteration":440,"passed_time":175.7048117,"remaining_time":222.7187975},
{"learn":[3.452405671],"iteration":441,"passed_time":175.9289344,"remaining_time":222.10032,
,
{"learn":[3.452001143],"iteration":442,"passed_time":176.1977994,"remaining_time":221.539896,
,
{"learn":[3.451730531],"iteration":443,"passed_time":176.4363781,"remaining_time":220.94285,
{,
{"learn":[3.451386572],"iteration":444,"passed_time":176.7452712,"remaining_time":220.43511,
{,
{"learn":[3.450856076],"iteration":445,"passed_time":176.9613763,"remaining_time":219.81301,,
{"learn":[3.450585405],"iteration":446,"passed_time":177.1888903,"remaining_time":219.206837,
,
{"learn":[3.449905721],"iteration":447,"passed_time":177.497091,"remaining_time":218.701772,
,
{"learn":[3.449552801],"iteration":448,"passed_time":177.7411351,"remaining_time":218.118854,,
{"learn":[3.449241544],"iteration":449,"passed_time":178.0099125,"remaining_time":217.5676708,,
{"learn":[3.448932169],"iteration":450,"passed_time":178.2656351,"remaining_time":217.0018485,,
{"learn":[3.448541701],"iteration":451,"passed_time":178.494482,"remaining_time":216.4048144},
{"learn":[3.448292759],"iteration":452,"passed_time":178.7173715,"remaining_time":21,
{"lear,
,
{"learn":[3.448076866],"iteration":453,"passed_time":178.9850302,"remaining_time":215.255124,
,
{"learn":[3.447793337],"iteration":454,"passed_time":179.2242456,"remaining_time":,
{"learn",
,
{"learn":[3.44736745],"iteration":455,"passed_time":179.460521,"remaining_time":21,
{"learn",
{"learn":[3.446918973],"iteration":456,"passed_time":179.7169838,"remaining_time":21,
{"learn",
{"learn":[3.446417062],"iteration":457,"passed_time":179.9851185,"remaining_time":2,
{"learn":,
{"learn":[3.445816629],"iteration":458,"passed_time":180.2601399,"remaining_time":212.4634764},
{"learn":[3.445748183],"iteration":459,"passed_time":180.4821912,"remaining_time":,
{"learn":[,
{"learn":[3.445492572],"iteration":460,"passed_time":180.7351479,"remaining_time",
{"learn":[3,
{"learn":[3.445319033],"iteration":461,"passed_time":180.9441691,"remaining_time,
{"learn":[3.,
{"learn":[3.444899988],"iteration":462,"passed_time":181.2190682,"remaining_time,
{"learn":[,,
{"learn":[3.444512639],"iteration":463,"passed_time":181.4883166,"remaining_time",
{"learn":,
,
{"learn":[3.444094397],"iteration":464,"passed_time":181.7437157,"remaining_time",
{"learn":[3,
{"learn":[3.443781358],"iteration":465,"passed_time":181.9735165,"remaining_time",
{"learn":[3,
{"learn":[3.443402775],"iteration":466,"passed_time":182.2305214,"remaining_time",
{"learn":[3,
{"learn":[3.442921258],"iteration":467,"passed_time":182.460779,"remaining_time",
{"learn":[3,
{"learn":[3.442664398],"iteration":468,"passed_time":182.7437495,"remaining_time,
{"learn":[3.,
{"learn":[3.442161424],"iteration":469,"passed_time":183.0411751,"remaining_time,
{"learn":[3.,
{"learn":[3.441717946],"iteration":470,"passed_time":183.2843844,"remaining_time":205.8544359},
{"learn":[3.441392337],"iteration":471,"passed_time":183.5415819,"remaining_time":205.3177017},
{"learn":[3.441053278],"iteration":472,"passed_time":183.8339331,"remaining_time":204.8213166},
{"learn":[3.440580444],"iteration":473,"passed_time":184.0890806,"remaining_time":204.2845072},
{"learn":[3.440276917],"iteration":474,"passed_time":184.3268866,"remaining_time":203.7297167},
{"learn":[3.439732678],"iteration":475,"passed_time":184.5652344,"remaining_tim,
{"learn":[3.4,
{"learn":[3.439212013],"iteration":476,"passed_time":184.8253313,"remaining_tim,
{"learn":[3.4,
{"learn":[3.438755069],"iteration":477,"passed_time":185.0945683,"remaining_tim,
{"learn":[3.,
{"learn":[3.438347811],"iteration":478,"passed_time":185.3089839,"remaining_time,
{"learn":[3.,
{"learn":[3.437979873],"iteration":479,"passed_time":185.6311285,"remaining_tim,
{"learn":[3.4,
{"learn":[3.43769391],"iteration":480,"passed_time":185.8227074,"remaining_time,
{"learn":[3.,
{"learn":[3.437368898],"iteration":481,"passed_time":186.1502191,"remaining_time,
{"learn":[3,
{"learn":[3.437156379],"iteration":482,"passed_time":186.3793653,"remaining_time",
{"learn":[3,
{"learn":[3.43648193],"iteration":483,"passed_time":186.6235971,"remaining_time",
{"learn":[3,
{"learn":[3.436161433],"iteration":484,"passed_time":186.921638,"remaining_time":,
{"learn":[,
{"learn":[3.435666045],"iteration":485,"passed_time":187.2290856,"remaining_time":,
{"learn":[,
{"learn":[3.435301037],"iteration":486,"passed_time":187.4876143,"remaining_time":,
{"learn",
{"learn":[3.434984191],"iteration":487,"passed_time":187.7516394,"remaining_time":19,
{"learn",
{"learn":[3.434739525],"iteration":488,"passed_time":187.9830789,"remaining_time":19,
{"learn",
{"learn":[3.434470795],"iteration":489,"passed_time":188.2178437,"remaining_time":19,
{"learn",
{"learn":[3.434059412],"iteration":490,"passed_time":188.4666946,"remaining_time":19,
{"learn",
{"learn":[3.433729539],"iteration":491,"passed_time":188.7384896,"remaining_time":19,
{"learn",
{"learn":[3.433330341],"iteration":492,"passed_time":189.0013383,"remaining_time":19,
{"learn",
{"learn":[3.432808953],"iteration":493,"passed_time":189.2396995,"remaining_time":19,
{"learn",
{"learn":[3.432388047],"iteration":494,"passed_time":189.4869519,"remaining_time":19,
{"learn",
{"learn":[3.432083467],"iteration":495,"passed_time":189.7338961,"remaining_time":1,
{"learn":,
{"learn":[3.431735432],"iteration":496,"passed_time":189.9636394,"remaining_time":1,
{"learn":,
{"learn":[3.431566551],"iteration":497,"passed_time":190.2277507,"remaining_time":1,
{"learn":,
{"learn":[3.43134847],"iteration":498,"passed_time":190.4586667,"remaining_time":19,
{"learn",
{"learn":[3.431061041],"iteration":499,"passed_time":190.6753497,"remaining_time":19,
{"learn",
{"learn":[3.430560909],"iteration":500,"passed_time":190.9225661,"remaining_time":19,
{"learn",
{"learn":[3.430090139],"iteration":501,"passed_time":191.1523102,"remaining_time":18,
{"learn",
{"learn":[3.429551596],"iteration":502,"passed_time":191.4235895,"remaining_time":18,
{"learn",
{"learn":[3.429151271],"iteration":503,"passed_time":191.7134048,"remaining_time":18,
{"learn",
{"learn":[3.428701197],"iteration":504,"passed_time":191.9842162,"remaining_time":18,
{"learn",
{"learn":[3.428463729],"iteration":505,"passed_time":192.2475639,"remaining_time":1,
{"learn":,
{"learn":[3.428262493],"iteration":506,"passed_time":192.4819276,"remaining_time":1,
{"learn":,
{"learn":[3.427960163],"iteration":507,"passed_time":192.7398057,"remaining_time":1,
{"learn":[3.42360791],"iteration":508,"passed_time":194.6799352,"remaining_time":187.7953796},
{"learn":[,
{"learn":[3.427154404],"iteration":509,"passed_time":193.3714753,"remaining_time",
{"learn":[3.422789441],"iteration":510,"passed_time":195.1360257,"remaining_time":186.7348661},
{"learn":[3.422361125],"iteration":511,"passed_time":195.4106076,"remaining_time":186.2507354},
{"learn":[3.42188588],"iteration":512,"passed_time":195.7240775,"remaining_time":185.8043387},
{"learn":[3.421506944],"iteration":513,"passed_time":195.9659162,"remaining_time":185.2907301},
{"learn":[3.421172563],"iteration":514,"passed_time":196.1995389,"remaining_time":184.7704395},
{"learn":[3.421038468],"iteration":515,"passed_time":196.4611273,"remaining_time":184.2774915},
{"learn":[3.420719301],"iteration":516,"passed_time":196.714009,"remaining_time":183.7773043},
{"learn":[3.420446291],"iteration":517,"passed_time":196.9439552,"remaining_time":183.2567305},
{"learn":[3.420202291],"iteration":518,"passed_time":197.1952813,"remaining_time":182.7570911},
{"learn":[3.419805511],"iteration":519,"passed_time":197.4596615,"remaining_time":182.2704568},
{"learn":[3.419523162],"iteration":520,"passed_time":197.6798085,"remaining_time":181.7440082},
{"learn":[3.419233472],"iteration":521,"passed_time":197.9525483,"remaining_time":181.2668929},
{"learn":[3.418934487],"iteration":522,"passed_time":198.1960765,"remaining_time":180.7639168},
{"learn":[3.418668923],"iteration":523,"passed_time":198.452826,"remaining_time":180.2739412},
{"learn":[3.418413674],"iteration":524,"passed_time":198.7152639,"remaining_time":179.7900007},
{"learn":[3.417989784],"iteration":525,"passed_time":198.9922069,"remaining_time":179.3199735},
{"learn":[3.417570196],"iteration":526,"passed_time":199.2685842,"remaining_time":178.8501714},
{"learn":[3.417311472],"iteration":527,"passed_time":199.5745454,"remaining_time":178.4075482},
{"learn":[3.416839068],"iteration":528,"passed_time":199.8096334,"remaining_time":177.902339},
{"learn":[3.416398687],"iteration":529,"passed_time":200.052228,"remaining_time":177.4048059},
{"learn":[3.415943215],"iteration":530,"passed_time":200.3512746,"remaining_time":176.9580938},
{"learn":[3.415665673],"iteration":531,"passed_time":200.6453114,"remaining_time":176.5075295},
{"learn":[3.415340485],"iteration":532,"passed_time":200.9340962,"remaining_time":176.0529511},
{"learn":[3.415020192],"iteration":533,"passed_time":201.16445,"remaining_time":175.5480032},
{"learn":[3.414729204],"iteration":534,"passed_time":201.368486,"remaining_time":175.0212075},
{"learn":[3.414458979],"iteration":535,"passed_time":201.6387874,"remaining_time":174.5529801},
{"learn":[3.414132067],"iteration":536,"passed_time":201.9235965,"remaining_time":174.0979985},
{"learn":[3.413781528],"iteration":537,"passed_time":202.1964164,"remaining_time":173.6333538},
{"learn":[3.41,
{"learn":[3.417469676],"iteration":538,"passed_time":200.9426496,"remaining_t,
{"learn":[3.412957578],"iteration":539,"passed_time":202.7958302,"remaining_time":172.7520035},
{"learn":[3.412590022],"iteration":540,"passed_time":203.0430665,"remaining_time":172.2675925},
{"learn":[3.412314215],"iteration":541,"passed_time":203.2746922,"remaining_time":171.7708654},
{"learn":[3.411980621],"iteration":542,"passed_time":203.5900862,"remaining_time":171.3456158},
{"learn":[3.411737685],"iteration":543,"passed_time":203.8485102,"remaining_time":170.8730159},
{"learn":[3.411343808],"iteration":544,"passed_time":204.0589982,"remaining_time":170.361182},
{"learn":[3.411059303],"iteration":545,"passed_time":204.296565,"remaining_time":169.8729679},
{"learn":[3.410797907],"iteration":546,"passed_time":204.5719503,"remaining_time":169.4169899},
{"learn":[3.410406138],"iteration":547,"passed_time":204.8811662,"remaining_time":168.989575},
{"learn":[3.410071924],"iteration":548,"passed_time":205.1809587,"remaining_time":168.5548495},
{"learn":[3.409729234],"iteration":549,"passed_time":205.4229048,"remaining_time":168.0732857},
{"learn":[3.409451719],"iteration":550,"passed_time":205.6600729,"remaining_time":167.5886982},
{"learn":[3.409113697],"iteration":551,"passed_time":205.9039738,"remaining_time":167.1104715},
{"learn":[3.408786872],"iteration":552,"passed_time":206.1679705,"remaining_time":166.649336},
{"learn":[3.40841663],"iteration":553,"passed_time":206.4208907,"remaining_time":166.179995},
{"learn":[3.408094287],"iteration":554,"passed_time":206.6898864,"remaining_time":165.7243233},
{"learn":[3.407831974],"iteration":555,"passed_time":206.9865324,"remaining_time":165.2914036},
{"learn":[3.407606388],"iteration":556,"passed_time":207.2185766,"remaining_time":164.8075933},
{"learn":[3.407389841],"iteration":557,"passed_time":207.4650841,"remaining_time":164.3361419},
{"learn":[3.407139834],"iteration":558,"passed_time":207.7489235,"remaining_time":163.8949468},
{"learn":[3.406661425],"iteration":559,"passed_time":207.9716364,"remaining_time":163.4062857},
{"learn":[3.406349736],"iteration":560,"passed_time":208.2569473,"remaining_time":162.9675577},
{"learn":[3.406133872],"iteration":561,"passed_time":208.5296281,"remaining_time":162.5195322},
{"learn":[3.405566703],"iteration":562,"passed_time":208.7808812,"remaining_time":162.0554975},
{"learn":[3.405285799],"iteration":563,"passed_time":208.9800569,"remaining_time":161.5519589},
{"lear,
{"learn":[3.409203576],"iteration":564,"passed_time":207.6911294,"remaining_time":159.,
{"learn":[3.404664196],"iteration":565,"passed_time":209.4905778,"remaining_time":160.634118},
{"learn,
{"learn":[3.408390442],"iteration":566,"passed_time":208.2202937,"remaining_time":159,
{"learn,
{"learn":[3.408101303],"iteration":567,"passed_time":208.5055887,"remaining_time":158,
{"learn,
{"learn":[3.4078019],"iteration":568,"passed_time":208.6845412,"remaining_time":158.0,
{"lea,
{"learn":[3.407460057],"iteration":569,"passed_time":208.9429758,"remaining_time":157.6,
{"lea,
{"learn":[3.407069866],"iteration":570,"passed_time":209.223445,"remaining_time":157.19,
{"le,
{"learn":[3.40666163],"iteration":571,"passed_time":209.4664636,"remaining_time":156.73,
{"le,
{"learn":[3.406274679],"iteration":572,"passed_time":209.7366214,"remaining_time":156.29,
{"le,
{"learn":[3.40594467],"iteration":573,"passed_time":210.015848,"remaining_time":155.865,
{"l,
{"learn":[3.40572172],"iteration":574,"passed_time":210.2550007,"remaining_time":155.4058,
{",
{"learn":[3.405264403],"iteration":575,"passed_time":210.5291715,"remaining_time":154.9728,
{",
{"learn":[3.404991867],"iteration":576,"passed_time":210.7811593,"remaining_time":154.52,
{"le,
{"learn":[3.404733879],"iteration":577,"passed_time":211.0475294,"remaining_time":154.08,
{"le,
{"learn":[3.40451931],"iteration":578,"passed_time":211.2984734,"remaining_time":153.638,
{"l,
{"learn":[3.404201341],"iteration":579,"passed_time":211.5412367,"remaining_time":153.185,
{"l,
{"learn":[3.403942256],"iteration":580,"passed_time":211.753095,"remaining_time":152.7100,
{",
{"learn":[3.403587629],"iteration":581,"passed_time":212.013173,"remaining_time":152.27062,
{,
{"learn":[3.403414257],"iteration":582,"passed_time":212.2322824,"remaining_time":151.80250,
{,
{"learn":[3.402954072],"iteration":583,"passed_time":212.4773251,"remaining_time":151.35371,
,
{"learn":[3.402439941],"iteration":584,"passed_time":212.9401626,"remaining_time":151.060115,
,
{"learn":[3.402004692],"iteration":585,"passed_time":213.2528343,"remaining_time":150.659852,
,
{"learn":[3.401746104],"iteration":586,"passed_time":213.5486583,"remaining_time":150.248033,
,
{"learn":[3.40139995],"iteration":587,"passed_time":213.8468997,"remaining_time":149.8383039,,
{"learn":[3.40112222],"iteration":588,"passed_time":214.1688496,"remaining_time":149.4454961},
{"learn":[3.400787265],"iteration":589,"passed_time":214.5082821,"remaining_time":149.0650774,,
{"learn":[3.400547003],"iteration":590,"passed_time":214.8200341,"remaining_time":148.6656412,,
{"learn":[3.400258052],"iteration":591,"passed_time":215.0881788,"remaining_time":148.2364475,,
{"learn":[3.399970659],"iteration":592,"passed_time":215.4577586,"remaining_time":147.8774161,,
{"learn":[3.399598547],"iteration":593,"passed_time":215.7428412,"remaining_time":147.4605952,,
{"learn":[3.39931592],"iteration":594,"passed_time":215.9963193,"remaining_time":147.0227047},
{"learn":[3.399056584],"iteration":595,"passed_time":216.2430934,"remaining_time":146.5808888},
{"learn":[3.398647143],"iteration":596,"passed_time":216.5089778,"remaining_time":146.1526266},
{"learn":[3.39829869],"iteration":597,"passed_time":216.7775748,"remaining_time":145.7267309},
{"learn":[3.397747439],"iteration":598,"passed_time":217.1400423,"remaining_time":145.364202},
{"learn":[3.39743809],"iteration":599,"passed_time":217.4615978,"remaining_time":144.9743985},
{"learn":[3.397193628],"iteration":600,"passed_time":217.7188247,"remaining_time":144.5421149},
{"learn":[3.396897091],"iteration":601,"passed_time":218.0375202,"remaining_time":144.1510515},
{"learn":[3.396587622],"iteration":602,"passed_time":218.3189086,"remaining_time":143.7356662},
{"learn":[3.396416727],"iteration":603,"passed_time":218.5315674,"remaining_time":143.2756634},
{"learn":[3.396040816],"iteration":604,"passed_time":218.8191159,"remaining_time":142.8653732},
{"learn":[3.395789549],"iteration":605,"passed_time":219.1076869,"remaining_time":142.4561529},
{"learn":[3.39540518],"iteration":606,"passed_time":219.4399622,"remaining_time":142.0756262},
{"learn":[3.395055164],"iteration":607,"passed_time":219.6677534,"remaining_time":141.6278936},
{"learn":[3.394600555],"iteration":608,"passed_time":219.9638159,"remaining_time":141.2247159},
{"learn":[3.394338009],"iteration":609,"passed_time":220.3314062,"remaining_time":140.8676203},
{"learn":[3.394054913],"iteration":610,"passed_time":220.5770651,"remaining_time":140.4328614},
{"learn":[3.393740671],"iteration":611,"passed_time":220.9349716,"remaining_time":140.069884},
{"learn":[3.393419492],"iteration":612,"passed_time":221.1838377,"remaining_time":139.6380835},
{"learn":[3.393209599],"iteration":613,"passed_time":221.5100644,"remaining_time":139.2555128},
{"learn":[3.393015474],"iteration":614,"passed_time":221.7645428,"remaining_time":138.8282097},
{"learn":[3.39271872],"iteration":615,"passed_time":222.039523,"remaining_time":138.4142481},
{"learn":[3.392463399],"iteration":616,"passed_time":222.3488093,"remaining_time":138.0220323},
{"learn":[3.392279023],"iteration":617,"passed_time":222.5903569,"remaining_time":137.5882141},
{"learn":[3.392031122],"iteration":618,"passed_time":222.8722624,"remaining_time":137.1798578},
{"learn":[3.391759662],"iteration":619,"passed_time":223.1235827,"remaining_time":136.7531636},
{"learn":[3.391428277],"iteration":620,"passed_time":223.4080271,"remaining_time":136.34725},
{"learn":[3.391203545],"iteration":621,"passed_time":223.6505942,"remaining_time":135.9162775},
{"learn":[3.390892938],"iteration":622,"passed_time":223.9402089,"remaining_time":135.5143801},
{"learn":[3.390597926],"iteration":623,"passed_time":224.345168,"remaining_time":135.1823448},
{"learn":[3.390402426],"iteration":624,"passed_time":224.6225354,"remaining_time":134.7735213},
{"learn":[3.390105366],"iteration":625,"passed_time":224.9344956,"remaining_time":134.3857849},
{"learn":[3.389888516],"iteration":626,"passed_time":225.1948817,"remaining_time":133.967609},
{"learn":[3.38958579],"iteration":627,"passed_time":225.4395833,"remaining_time":133.5406449},
{"learn":[3.389364256],"iteration":628,"passed_time":225.6904694,"remaining_time":133.117908},
{"learn":[3.388942695],"iteration":629,"passed_time":225.9887958,"remaining_time":132.7235785},
{"learn":[3.388675498],"iteration":630,"passed_time":226.2226266,"remaining_time":132.2918371},
{"learn":[3.38843922],"iteration":631,"passed_time":226.4331534,"remaining_time":131.8471526},
{"learn":[3.388162397],"iteration":632,"passed_time":226.6860497,"remaining_time":131.4277729},
{"learn":[3.388047543],"iteration":633,"passed_time":226.9383636,"remaining_time":131.0085821},
{"learn":[3.387812846],"iteration":634,"passed_time":227.2511859,"remaining_time":130.6246974},
{"learn":[3.387496836],"iteration":635,"passed_time":227.4894476,"remaining_time":130.1983631},
{"learn":[3.387260421],"iteration":636,"passed_time":227.7324882,"remaining_time":129.7753426},
{"learn":[3.386698487],"iteration":637,"passed_time":228.066027,"remaining_time":129.4042347},
{"learn":[3.3864226],"iteration":638,"passed_time":228.2758483,"remaining_time":128.9633509},
{"learn":[3.386204194],"iteration":639,"passed_time":228.4556453,"remaining_time":128.5063005},
{"learn":[3.385880765],"iteration":640,"passed_time":228.7033351,"remaining_time":128.0881393},
{"learn":[3.385509672],"iteration":641,"passed_time":228.9650456,"remaining_time":127.6783276},
{"learn":[3.385193676],"iteration":642,"passed_time":229.2793692,"remaining_time":127.2981879},
{"learn":[3.38505],"iteration":643,"passed_time":229.5300582,"remaining_time":126.8830757},
{"learn":[3.384865165],"iteration":644,"passed_time":229.7950991,"remaining_time":126.4763724},
{"learn":[3.384635321],"iteration":645,"passed_time":230.1401898,"remaining_time":126.113974},
{"learn":[3.384422912],"iteration":646,"passed_time":230.4706041,"remaining_time":125.7436217},
{"learn":[3.384202171],"iteration":647,"passed_time":230.8131043,"remaining_time":125.3799579},
{"learn":[3.383961484],"iteration":648,"passed_time":231.1658662,"remaining_time":125.0219091},
{"learn":[3.383677494],"iteration":649,"passed_time":231.4812182,"remaining_time":124.6437329},
{"learn":[3.38345144],"iteration":650,"passed_time":231.8487975,"remaining_time":124.2937486},
{"learn":[3.383195764],"iteration":651,"passed_time":232.1760987,"remaining_time":123.9222122},
{"learn":[3.382859844],"iteration":652,"passed_time":232.4170241,"remaining_time":123.5049117},
{"learn":[3.382715901],"iteration":653,"passed_time":232.6658959,"remaining_time":123.0923547},
{"learn":[3.382481154],"iteration":654,"passed_time":232.9986798,"remaining_time":122.7244955},
{"learn":[3.382167363],"iteration":655,"passed_time":233.2707601,"remaining_time":122.3249108},
{"learn":[3.38197397],"iteration":656,"passed_time":233.5556356,"remaining_time":121.9323943},
{"learn":[3.381666436],"iteration":657,"passed_time":233.825479,"remaining_time":121.5323918},
{"learn":[3.381343227],"iteration":658,"passed_time":234.0873089,"remaining_time":121.1286378},
{"learn":[3.381142899],"iteration":659,"passed_time":234.3517131,"remaining_time":120.7266401},
{"learn":[3.380824895],"iteration":660,"passed_time":234.6283746,"remaining_time":120.3313449},
{"learn":[3.380582054],"iteration":661,"passed_time":234.9175035,"remaining_time":119.9427737},
{"learn":[3.380365966],"iteration":662,"passed_time":235.1077601,"remaining_time":119.5042461},
{"learn":[3.380053747],"iteration":663,"passed_time":235.368966,"remaining_time":119.1023683},
{"learn":[3.379670195],"iteration":664,"passed_time":235.645002,"remaining_time":118.7083845},
{"learn":[3.379422761],"iteration":665,"passed_time":235.9465786,"remaining_time":118.3275634},
{"learn":[3.379161048],"iteration":666,"passed_time":236.319893,"remaining_time":117.9827952},
{"learn":[3.378857911],"iteration":667,"passed_time":236.5485021,"remaining_time":117.566022},
{"learn":[3.378610783],"iteration":668,"passed_time":236.7960748,"remaining_time":117.159194},
{"learn":[3.37833377],"iteration":669,"passed_time":237.1096431,"remaining_time":116.7853466},
{"learn":[3.378132447],"iteration":670,"passed_time":237.3343058,"remaining_time":116.3680873},
{"learn":[3.377980591],"iteration":671,"passed_time":237.5630394,"remaining_time":115.9533883},
{"learn":[3.377675484],"iteration":672,"passed_time":237.8698409,"remaining_time":115.5771738},
{"learn":[3.377440777],"iteration":673,"passed_time":238.1607725,"remaining_time":115.1934893},
{"learn":[3.377122639],"iteration":674,"passed_time":238.483969,"remaining_time":114.8256147},
{"learn":[3.376892148],"iteration":675,"passed_time":238.7093707,"remaining_time":114.4110002},
{"learn":[3.376715765],"iteration":676,"passed_time":239.0010116,"remaining_time":114.0285476},
{"learn":[3.376509242],"iteration":677,"passed_time":239.2999187,"remaining_time":113.6498139},
{"learn":[3.376343912],"iteration":678,"passed_time":239.6277835,"remaining_time":113.2850052},
{"learn":[3.376157999],"iteration":679,"passed_time":239.8337836,"remaining_time":112.862957},
{"learn":[3.375846782],"iteration":680,"passed_time":240.1140915,"remaining_time":112.4763512},
{"learn":[3.375615316],"iteration":681,"passed_time":240.4044494,"remaining_time":112.0947433},
{"learn":[3.375337862],"iteration":682,"passed_time":240.6421879,"remaining_time":111.6889803},
{"learn":[3.375133096],"iteration":683,"passed_time":240.9142929,"remaining_time":111.2995856},
{"learn":[3.374790025],"iteration":684,"passed_time":241.183367,"remaining_time":110.9091396},
{"learn":[3.374614615],"iteration":685,"passed_time":241.4793466,"remaining_time":110.5313627},
{"learn":[3.374438074],"iteration":686,"passed_time":241.7007499,"remaining_time":110.1198467},
{"learn":[3.374150369],"iteration":687,"passed_time":241.9970924,"remaining_time":109.7428675},
{"learn":[3.373999686],"iteration":688,"passed_time":242.2583687,"remaining_time":109.3502942},
{"learn":[3.373723919],"iteration":689,"passed_time":242.5008169,"remaining_time":108.9496424},
{"learn":[3.373471147],"iteration":690,"passed_time":242.7549926,"remaining_time":108.5546928},
{"learn":[3.373196858],"iteration":691,"passed_time":243.0227017,"remaining_time":108.1661736},
{"learn":[3.372962555],"iteration":692,"passed_time":243.3087805,"remaining_time":107.7861409},
{"learn":[3.372627082],"iteration":693,"passed_time":243.5403134,"remaining_time":107.3823284},
{"learn":[3.37244209],"iteration":694,"passed_time":243.8018352,"remaining_time":106.9921723},
{"learn":[3.372163718],"iteration":695,"passed_time":244.0999387,"remaining_time":106.618364},
{"learn":[3.372024242],"iteration":696,"passed_time":244.319812,"remaining_time":106.2107648},
{"learn":[3.371880835],"iteration":697,"passed_time":244.5842551,"remaining_time":105.8229872},
{"learn":[3.371715693],"iteration":698,"passed_time":244.7737964,"remaining_time":105.4033086},
{"learn":[3.371452279],"iteration":699,"passed_time":245.0290643,"remaining_time":105.0124561},
{"learn":[3.371288829],"iteration":700,"passed_time":245.2982236,"remaining_time":104.6279156},
{"learn":[3.371033119],"iteration":701,"passed_time":245.5658267,"remaining_time":104.2430432},
{"learn":[3.370899482],"iteration":702,"passed_time":246.0828195,"remaining_time":103.9638654},
{"learn":[3.370705477],"iteration":703,"passed_time":246.4611134,"remaining_time":103.6256954},
{"learn":[3.37040944],"iteration":704,"passed_time":246.8341222,"remaining_time":103.2852001},
{"learn":[3.370170725],"iteration":705,"passed_time":247.2996085,"remaining_time":102.9831231},
{"learn":[3.369898543],"iteration":706,"passed_time":247.6758927,"remaining_time":102.6436161},
{"learn":[3.369593041],"iteration":707,"passed_time":248.0212607,"remaining_time":102.2912544},
{"learn":[3.369275414],"iteration":708,"passed_time":248.4352571,"remaining_time":101.9670801},
{"learn":[3.368939628],"iteration":709,"passed_time":248.8332827,"remaining_time":101.6361296},
{"learn":[3.368642166],"iteration":710,"passed_time":249.1941368,"remaining_time":101.2898812},
{"learn":[3.368322433],"iteration":711,"passed_time":249.4860553,"remaining_time":100.9157078},
{"learn":[3.368021877],"iteration":712,"passed_time":249.9851045,"remaining_time":100.6251403},
{"learn":[3.367857721],"iteration":713,"passed_time":250.2604257,"remaining_time":100.2443722},
{"learn":[3.367686091],"iteration":714,"passed_time":250.5428169,"remaining_time":99.86671724},
{"learn":[3.367343715],"iteration":715,"passed_time":250.8957838,"remaining_time":99.51732207},
{"learn":[3.366850138],"iteration":716,"passed_time":251.1320226,"remaining_time":99.12184437},
{"learn":[3.366664977],"iteration":717,"passed_time":251.5137193,"remaining_time":98.7839399},
{"learn":[3.366500201],"iteration":718,"passed_time":251.867571,"remaining_time":98.43503124},
{"learn":[3.366218687],"iteration":719,"passed_time":252.1752241,"remaining_time":98.06814271},
{"learn":[3.366044096],"iteration":720,"passed_time":252.4791258,"remaining_time":97.69996686},
{"learn":[3.3659347],"iteration":721,"passed_time":252.73088,"remaining_time":97.31189008},
{"learn":[3.365701577],"iteration":722,"passed_time":253.0135414,"remaining_time":96.93603177},
{"learn":[3.365469166],"iteration":723,"passed_time":253.2472709,"remaining_time":96.5417773},
{"learn":[3.36533729],"iteration":724,"passed_time":253.4958013,"remaining_time":96.1535798},
{"learn":[3.364994157],"iteration":725,"passed_time":253.7851778,"remaining_time":95.78118281},
{"learn":[3.36473253],"iteration":726,"passed_time":254.1482458,"remaining_time":95.43668653},
{"learn":[3.364486791],"iteration":727,"passed_time":254.4139938,"remaining_time":95.05577789},
{"learn":[3.364296793],"iteration":728,"passed_time":254.6416746,"remaining_time":94.66103403},
{"learn":[3.364174319],"iteration":729,"passed_time":254.9399642,"remaining_time":94.29286347},
{"learn":[3.363967557],"iteration":730,"passed_time":255.1862522,"remaining_time":93.90574807},
{"learn":[3.363740401],"iteration":731,"passed_time":255.3817895,"remaining_time":93.50043658},
{"learn":[3.363406827],"iteration":732,"passed_time":255.686897,"remaining_time":93.13560914},
{"learn":[3.363213784],"iteration":733,"passed_time":256.0773018,"remaining_time":92.80185596},
{"learn":[3.362824913],"iteration":734,"passed_time":256.3831783,"remaining_time":92.43747244},
{"learn":[3.36258456],"iteration":735,"passed_time":256.6318574,"remaining_time":92.05273148},
{"learn":[3.362351479],"iteration":736,"passed_time":256.8694533,"remaining_time":91.66440465},
{"learn":[3.362202465],"iteration":737,"passed_time":257.1684798,"remaining_time":91.29829501},
{"learn":[3.361997975],"iteration":738,"passed_time":257.3998301,"remaining_time":90.90846504},
{"learn":[3.361926378],"iteration":739,"passed_time":257.6302716,"remaining_time":90.51874408},
{"learn":[3.361535424],"iteration":740,"passed_time":257.9691909,"remaining_time":90.16736901},
{"learn":[3.361431627],"iteration":741,"passed_time":258.2243189,"remaining_time":89.78689257},
{"learn":[3.361148725],"iteration":742,"passed_time":258.4667516,"remaining_time":89.40236228},
{"learn":[3.360974462],"iteration":743,"passed_time":258.669189,"remaining_time":89.00445213},
{"learn":[3.360655811],"iteration":744,"passed_time":258.8978343,"remaining_time":88.61603724},
{"learn":[3.360358575],"iteration":745,"passed_time":259.1869532,"remaining_time":88.2486409},
{"learn":[3.360240052],"iteration":746,"passed_time":259.4155373,"remaining_time":87.86095171},
{"learn":[3.35999639],"iteration":747,"passed_time":259.7154907,"remaining_time":87.49773215},
{"learn":[3.359758431],"iteration":748,"passed_time":260.0851371,"remaining_time":87.1580366},
{"learn":[3.359616653],"iteration":749,"passed_time":260.4047035,"remaining_time":86.80156785},
{"learn":[3.359321581],"iteration":750,"passed_time":260.7125392,"remaining_time":86.44130793},
{"learn":[3.359127588],"iteration":751,"passed_time":261.0464022,"remaining_time":86.08977093},
{"learn":[3.35890519],"iteration":752,"passed_time":261.3120969,"remaining_time":85.71592023},
{"learn":[3.358619523],"iteration":753,"passed_time":261.5697813,"remaining_time":85.33974296},
{"learn":[3.35844241],"iteration":754,"passed_time":261.8484243,"remaining_time":84.97068074},
{"learn":[3.358207744],"iteration":755,"passed_time":262.1370943,"remaining_time":84.60509394},
{"learn":[3.358029967],"iteration":756,"passed_time":262.4533255,"remaining_time":84.2485576},
{"learn":[3.357944229],"iteration":757,"passed_time":262.6781161,"remaining_time":83.86293415},
{"learn":[3.357616043],"iteration":758,"passed_time":262.8822021,"remaining_time":83.47116036},
{"learn":[3.357342335],"iteration":759,"passed_time":263.1598915,"remaining_time":83.10312364},
{"learn":[3.357168982],"iteration":760,"passed_time":263.3921672,"remaining_time":82.72106172},
{"learn":[3.356945143],"iteration":761,"passed_time":263.6499941,"remaining_time":82.34737349},
{"learn":[3.356796789],"iteration":762,"passed_time":263.91438,"remaining_time":81.9760263},
{"learn":[3.356552758],"iteration":763,"passed_time":264.4135037,"remaining_time":81.67746974},
{"learn":[3.356310491],"iteration":764,"passed_time":264.6995343,"remaining_time":81.31292882},
{"learn":[3.356085918],"iteration":765,"passed_time":264.9966854,"remaining_time":80.95199007},
{"learn":[3.355929423],"iteration":766,"passed_time":265.3168813,"remaining_time":80.59821816},
{"learn":[3.355756806],"iteration":767,"passed_time":265.6137612,"remaining_time":80.23749036},
{"learn":[3.355576278],"iteration":768,"passed_time":265.9023557,"remaining_time":79.87443975},
{"learn":[3.355402833],"iteration":769,"passed_time":266.188236,"remaining_time":79.51077178},
{"learn":[3.355127678],"iteration":770,"passed_time":266.4368887,"remaining_time":79.13624839},
{"learn":[3.354958144],"iteration":771,"passed_time":266.7404717,"remaining_time":78.77827401},
{"learn":[3.354612064],"iteration":772,"passed_time":266.9763358,"remaining_time":78.40055399},
{"learn":[3.354345815],"iteration":773,"passed_time":267.2406774,"remaining_time":78.03151561},
{"learn":[3.354208865],"iteration":774,"passed_time":267.4726827,"remaining_time":77.65335949},
{"learn":[3.354018329],"iteration":775,"passed_time":267.7185717,"remaining_time":77.27958772},
{"learn":[3.353862407],"iteration":776,"passed_time":267.9356658,"remaining_time":76.89788091},
{"learn":[3.353571035],"iteration":777,"passed_time":268.2232035,"remaining_time":76.53669816},
{"learn":[3.353364956],"iteration":778,"passed_time":268.5657745,"remaining_time":76.19131729},
{"learn":[3.353164202],"iteration":779,"passed_time":268.8855165,"remaining_time":75.83950466},
{"learn":[3.352937281],"iteration":780,"passed_time":269.1665369,"remaining_time":75.47691624},
{"learn":[3.352725788],"iteration":781,"passed_time":269.4255764,"remaining_time":75.10840875},
{"learn":[3.352587944],"iteration":782,"passed_time":269.7360754,"remaining_time":74.75444234},
{"learn":[3.352401288],"iteration":783,"passed_time":270.051573,"remaining_time":74.40196399},
{"learn":[3.352191379],"iteration":784,"passed_time":270.3055952,"remaining_time":74.03274263},
{"learn":[3.351925919],"iteration":785,"passed_time":270.5659373,"remaining_time":73.66553509},
{"learn":[3.351566905],"iteration":786,"passed_time":270.8756869,"remaining_time":73.31197117},
{"learn":[3.351344798],"iteration":787,"passed_time":271.1819277,"remaining_time":72.95757444},
{"learn":[3.351225933],"iteration":788,"passed_time":271.4369768,"remaining_time":72.58960977},
{"learn":[3.351033049],"iteration":789,"passed_time":271.7193182,"remaining_time":72.22918586},
{"learn":[3.350837978],"iteration":790,"passed_time":272.0348643,"remaining_time":71.87773279},
{"learn":[3.350659535],"iteration":791,"passed_time":272.3267558,"remaining_time":71.52015808},
{"learn":[3.350479653],"iteration":792,"passed_time":272.5441286,"remaining_time":71.14329712},
{"learn":[3.350296634],"iteration":793,"passed_time":272.8937722,"remaining_time":70.801155},
{"learn":[3.350149407],"iteration":794,"passed_time":273.1317174,"remaining_time":70.43019128},
{"learn":[3.349963447],"iteration":795,"passed_time":273.4123977,"remaining_time":70.07051399},
{"learn":[3.349815039],"iteration":796,"passed_time":273.6870175,"remaining_time":69.70949129},
{"learn":[3.349674282],"iteration":797,"passed_time":273.9712812,"remaining_time":69.35112631},
{"learn":[3.349510429],"iteration":798,"passed_time":274.2304983,"remaining_time":68.986646},
{"learn":[3.349374153],"iteration":799,"passed_time":274.4559627,"remaining_time":68.61399069},
{"learn":[3.349117551],"iteration":800,"passed_time":274.7824179,"remaining_time":68.26679295},
{"learn":[3.348936153],"iteration":801,"passed_time":275.0825039,"remaining_time":67.91313687},
{"learn":[3.348727268],"iteration":802,"passed_time":275.3419555,"remaining_time":67.54964536},
{"learn":[3.348555798],"iteration":803,"passed_time":275.6155555,"remaining_time":67.18986178},
{"learn":[3.348356162],"iteration":804,"passed_time":275.9032438,"remaining_time":66.83370503},
{"learn":[3.348081867],"iteration":805,"passed_time":276.2151876,"remaining_time":66.48355632},
{"learn":[3.347880936],"iteration":806,"passed_time":276.4822934,"remaining_time":66.12277896},
{"learn":[3.347633163],"iteration":807,"passed_time":276.7235011,"remaining_time":65.75607947},
{"learn":[3.347330207],"iteration":808,"passed_time":277.0357905,"remaining_time":65.40647218},
{"learn":[3.347064099],"iteration":809,"passed_time":277.3122972,"remaining_time":65.04856355},
{"learn":[3.346883836],"iteration":810,"passed_time":277.5293126,"remaining_time":64.67699146},
{"learn":[3.346507933],"iteration":811,"passed_time":277.7741411,"remaining_time":64.31223955},
{"learn":[3.346338564],"iteration":812,"passed_time":278.0167013,"remaining_time":63.94726093},
{"learn":[3.346129305],"iteration":813,"passed_time":278.3428594,"remaining_time":63.60168532},
{"learn":[3.345997436],"iteration":814,"passed_time":278.5817582,"remaining_time":63.23635003},
{"learn":[3.345858252],"iteration":815,"passed_time":278.8719738,"remaining_time":62.88289606},
{"learn":[3.345623105],"iteration":816,"passed_time":279.1460833,"remaining_time":62.52598929},
{"learn":[3.34543645],"iteration":817,"passed_time":279.4871093,"remaining_time":62.18417346},
{"learn":[3.345298702],"iteration":818,"passed_time":279.7162691,"remaining_time":61.817637},
{"learn":[3.345186848],"iteration":819,"passed_time":279.9863753,"remaining_time":61.46042384},
{"learn":[3.344985978],"iteration":820,"passed_time":280.2344346,"remaining_time":61.09861607},
{"learn":[3.344788171],"iteration":821,"passed_time":280.5609409,"remaining_time":60.75407237},
{"learn":[3.34458097],"iteration":822,"passed_time":280.8412803,"remaining_time":60.39964352},
{"learn":[3.344338782],"iteration":823,"passed_time":281.1139349,"remaining_time":60.04375309},
{"learn":[3.34416008],"iteration":824,"passed_time":281.3519683,"remaining_time":59.68072054},
{"learn":[3.344062298],"iteration":825,"passed_time":281.6261765,"remaining_time":59.32561102},
{"learn":[3.34388919],"iteration":826,"passed_time":281.9269157,"remaining_time":58.97624718},
{"learn":[3.343660261],"iteration":827,"passed_time":282.1573331,"remaining_time":58.61239287},
{"learn":[3.343391771],"iteration":828,"passed_time":282.3894414,"remaining_time":58.24920926},
{"learn":[3.343122798],"iteration":829,"passed_time":282.6792271,"remaining_time":57.89815494},
{"learn":[3.342928774],"iteration":830,"passed_time":282.943836,"remaining_time":57.54212791},
{"learn":[3.34271305],"iteration":831,"passed_time":283.1635846,"remaining_time":57.17726228},
{"learn":[3.342385454],"iteration":832,"passed_time":283.485181,"remaining_time":56.83316354},
{"learn":[3.342171132],"iteration":833,"passed_time":283.7273091,"remaining_time":56.47330133},
{"learn":[3.342021009],"iteration":834,"passed_time":283.938725,"remaining_time":56.10765225},
{"learn":[3.3418451],"iteration":835,"passed_time":284.1892419,"remaining_time":55.75004268},
{"learn":[3.341700361],"iteration":836,"passed_time":284.4079916,"remaining_time":55.38650255},
{"learn":[3.341504404],"iteration":837,"passed_time":284.6557092,"remaining_time":55.02890798},
{"learn":[3.341359947],"iteration":838,"passed_time":284.8962579,"remaining_time":54.67019967},
{"learn":[3.341173443],"iteration":839,"passed_time":285.1877813,"remaining_time":54.32148214},
{"learn":[3.341077892],"iteration":840,"passed_time":285.4132037,"remaining_time":53.96040355},
{"learn":[3.340983539],"iteration":841,"passed_time":285.611915,"remaining_time":53.59463489},
{"learn":[3.340828656],"iteration":842,"passed_time":285.8944077,"remaining_time":53.24486596},
{"learn":[3.340643056],"iteration":843,"passed_time":286.1860074,"remaining_time":52.89693975},
{"learn":[3.340503861],"iteration":844,"passed_time":286.4097028,"remaining_time":52.53669105},
{"learn":[3.340364916],"iteration":845,"passed_time":286.627731,"remaining_time":52.17573354},
{"learn":[3.34022478],"iteration":846,"passed_time":286.9035227,"remaining_time":51.82554778},
{"learn":[3.340070938],"iteration":847,"passed_time":287.1977174,"remaining_time":51.47883613},
{"learn":[3.339842646],"iteration":848,"passed_time":287.4583266,"remaining_time":51.12627482},
{"learn":[3.339620675],"iteration":849,"passed_time":287.7043583,"remaining_time":50.77135734},
{"learn":[3.339376971],"iteration":850,"passed_time":287.9485879,"remaining_time":50.41638025},
{"learn":[3.339136024],"iteration":851,"passed_time":288.2121583,"remaining_time":50.0650228},
{"learn":[3.338998598],"iteration":852,"passed_time":288.4587043,"remaining_time":49.71093731},
{"learn":[3.338755025],"iteration":853,"passed_time":288.6941776,"remaining_time":49.3552107},
{"learn":[3.338245586],"iteration":854,"passed_time":288.9328308,"remaining_time":49.00030464},
{"learn":[3.338132399],"iteration":855,"passed_time":289.1491299,"remaining_time":48.6419097},
{"learn":[3.337868341],"iteration":856,"passed_time":289.4281605,"remaining_time":48.29431383},
{"learn":[3.337689678],"iteration":857,"passed_time":289.6832638,"remaining_time":47.94291779},
{"learn":[3.337587498],"iteration":858,"passed_time":289.9333373,"remaining_time":47.59092033},
{"learn":[3.33743725],"iteration":859,"passed_time":290.2017243,"remaining_time":47.24214116},
{"learn":[3.337364509],"iteration":860,"passed_time":290.4320389,"remaining_time":46.88740234},
{"learn":[3.337140937],"iteration":861,"passed_time":290.7138599,"remaining_time":46.54119799},
{"learn":[3.336888086],"iteration":862,"passed_time":291.0994685,"remaining_time":46.21161899},
{"learn":[3.336719915],"iteration":863,"passed_time":291.3870372,"remaining_time":45.86647807},
{"learn":[3.33650504],"iteration":864,"passed_time":291.615218,"remaining_time":45.51220165},
{"learn":[3.336312045],"iteration":865,"passed_time":291.8932799,"remaining_time":45.16593477},
{"learn":[3.336097294],"iteration":866,"passed_time":292.2297574,"remaining_time":44.82878631},
{"learn":[3.33591964],"iteration":867,"passed_time":292.430552,"remaining_time":44.4710056},
{"learn":[3.335809157],"iteration":868,"passed_time":292.7119594,"remaining_time":44.12573841},
{"learn":[3.335693257],"iteration":869,"passed_time":293.0841515,"remaining_time":43.79418356},
{"learn":[3.335556699],"iteration":870,"passed_time":293.3211575,"remaining_time":43.44251357},
{"learn":[3.335392876],"iteration":871,"passed_time":293.6267615,"remaining_time":43.10117601},
{"learn":[3.335085643],"iteration":872,"passed_time":294.0667292,"remaining_time":42.7794669},
{"learn":[3.334844089],"iteration":873,"passed_time":294.3831239,"remaining_time":42.43967233},
{"learn":[3.334784394],"iteration":874,"passed_time":294.8032274,"remaining_time":42.11474677},
{"learn":[3.334359201],"iteration":875,"passed_time":295.0487403,"remaining_time":41.76489018},
{"learn":[3.334203909],"iteration":876,"passed_time":295.404766,"remaining_time":41.43077106},
{"learn":[3.33402764],"iteration":877,"passed_time":295.6627675,"remaining_time":41.08298137},
{"learn":[3.333851192],"iteration":878,"passed_time":296.0031257,"remaining_time":40.74673288},
{"learn":[3.333716533],"iteration":879,"passed_time":296.2929184,"remaining_time":40.40357978},
{"learn":[3.333439884],"iteration":880,"passed_time":296.5244759,"remaining_time":40.05268176},
{"learn":[3.333246652],"iteration":881,"passed_time":296.7774653,"remaining_time":39.70492166},
{"learn":[3.332795301],"iteration":882,"passed_time":297.0401289,"remaining_time":39.35865808},
{"learn":[3.332636664],"iteration":883,"passed_time":297.2751056,"remaining_time":39.00895051},
{"learn":[3.33248154],"iteration":884,"passed_time":297.5415731,"remaining_time":38.66359425},
{"learn":[3.332361865],"iteration":885,"passed_time":297.7751302,"remaining_time":38.31418154},
{"learn":[3.332142904],"iteration":886,"passed_time":298.0359078,"remaining_time":37.96849784},
{"learn":[3.331970259],"iteration":887,"passed_time":298.2683473,"remaining_time":37.61943119},
{"learn":[3.331726134],"iteration":888,"passed_time":298.5822542,"remaining_time":37.2807989},
{"learn":[3.331520431],"iteration":889,"passed_time":298.809932,"remaining_time":36.93156463},
{"learn":[3.331146351],"iteration":890,"passed_time":299.0606044,"remaining_time":36.58541625},
{"learn":[3.331021711],"iteration":891,"passed_time":299.3258704,"remaining_time":36.24124888},
{"learn":[3.330725653],"iteration":892,"passed_time":299.6475874,"remaining_time":35.90402223},
{"learn":[3.330518397],"iteration":893,"passed_time":299.997723,"remaining_time":35.57019982},
{"learn":[3.330264413],"iteration":894,"passed_time":300.2456616,"remaining_time":35.22435136},
{"learn":[3.330124594],"iteration":895,"passed_time":300.5100688,"remaining_time":34.88063298},
{"learn":[3.32993565],"iteration":896,"passed_time":300.8401236,"remaining_time":34.54462957},
{"learn":[3.329713615],"iteration":897,"passed_time":301.0941766,"remaining_time":34.20000669},
{"learn":[3.329460221],"iteration":898,"passed_time":301.4112893,"remaining_time":33.86266987},
{"learn":[3.329277723],"iteration":899,"passed_time":301.6891064,"remaining_time":33.52101183},
{"learn":[3.329158353],"iteration":900,"passed_time":301.9658303,"remaining_time":33.17937536},
{"learn":[3.329028802],"iteration":901,"passed_time":302.2151494,"remaining_time":32.83490537},
{"learn":[3.328856624],"iteration":902,"passed_time":302.5174248,"remaining_time":32.49633467},
{"learn":[3.328651263],"iteration":903,"passed_time":302.7691984,"remaining_time":32.15248125},
{"learn":[3.328421314],"iteration":904,"passed_time":303.0408153,"remaining_time":31.81091432},
{"learn":[3.328285713],"iteration":905,"passed_time":303.3309449,"remaining_time":31.47142254},
{"learn":[3.328106831],"iteration":906,"passed_time":303.5952301,"remaining_time":31.12938963},
{"learn":[3.32793415],"iteration":907,"passed_time":303.889465,"remaining_time":30.79056253},
{"learn":[3.327763195],"iteration":908,"passed_time":304.1802847,"remaining_time":30.45149165},
{"learn":[3.327525345],"iteration":909,"passed_time":304.4777327,"remaining_time":30.11318235},
{"learn":[3.327414125],"iteration":910,"passed_time":304.8587166,"remaining_time":29.78312379},
{"learn":[3.327245198],"iteration":911,"passed_time":305.1449035,"remaining_time":29.44380648},
{"learn":[3.327121633],"iteration":912,"passed_time":305.4231424,"remaining_time":29.10384818},
{"learn":[3.326951145],"iteration":913,"passed_time":305.7611156,"remaining_time":28.76964545},
{"learn":[3.326732685],"iteration":914,"passed_time":305.9485687,"remaining_time":28.42145174},
{"learn":[3.326556754],"iteration":915,"passed_time":306.1761589,"remaining_time":28.07728968},
{"learn":[3.326353201],"iteration":916,"passed_time":306.3934058,"remaining_time":27.73244567},
{"learn":[3.326242904],"iteration":917,"passed_time":306.5633395,"remaining_time":27.38365342},
{"learn":[3.325948043],"iteration":918,"passed_time":306.8091958,"remaining_time":27.04194217},
{"learn":[3.32577832],"iteration":919,"passed_time":307.0029557,"remaining_time":26.69590919},
{"learn":[3.325622996],"iteration":920,"passed_time":307.3135103,"remaining_time":26.3602251},
{"learn":[3.325368052],"iteration":921,"passed_time":307.5313483,"remaining_time":26.01675181},
{"learn":[3.325219424],"iteration":922,"passed_time":307.6638701,"remaining_time":25.66643336},
{"learn":[3.325089466],"iteration":923,"passed_time":307.8717604,"remaining_time":25.32278549},
{"learn":[3.324863541],"iteration":924,"passed_time":308.211678,"remaining_time":24.99013605},
{"learn":[3.324764093],"iteration":925,"passed_time":308.4675389,"remaining_time":24.65075365},
{"learn":[3.324616383],"iteration":926,"passed_time":308.6623907,"remaining_time":24.30674705},
{"learn":[3.324471388],"iteration":927,"passed_time":308.842189,"remaining_time":23.96189397},
{"learn":[3.32436793],"iteration":928,"passed_time":309.04195,"remaining_time":23.61892191},
{"learn":[3.324237307],"iteration":929,"passed_time":309.2839827,"remaining_time":23.27943956},
{"learn":[3.324052533],"iteration":930,"passed_time":309.503374,"remaining_time":22.93848851},
{"learn":[3.323922902],"iteration":931,"passed_time":309.6941186,"remaining_time":22.59570822},
{"learn":[3.323788185],"iteration":932,"passed_time":309.9237655,"remaining_time":22.25604747},
{"learn":[3.323636503],"iteration":933,"passed_time":310.1432322,"remaining_time":21.91590292},
{"learn":[3.323452486],"iteration":934,"passed_time":310.3218064,"remaining_time":21.57317371},
{"learn":[3.323297713],"iteration":935,"passed_time":310.5542128,"remaining_time":21.23447609},
{"learn":[3.32307344],"iteration":936,"passed_time":310.8123481,"remaining_time":20.89773525},
{"learn":[3.322975417],"iteration":937,"passed_time":311.0591852,"remaining_time":20.56041523},
{"learn":[3.322784747],"iteration":938,"passed_time":311.2149603,"remaining_time":20.21737228},
{"learn":[3.322652643],"iteration":939,"passed_time":311.4189468,"remaining_time":19.87780511},
{"learn":[3.322473245],"iteration":940,"passed_time":311.6252676,"remaining_time":19.53867246},
{"learn":[3.322229134],"iteration":941,"passed_time":311.8361221,"remaining_time":19.20010094},
{"learn":[3.322118607],"iteration":942,"passed_time":312.0634868,"remaining_time":18.86279825},
{"learn":[3.321958445],"iteration":943,"passed_time":312.2614968,"remaining_time":18.5239871},
{"learn":[3.321713573],"iteration":944,"passed_time":312.4692709,"remaining_time":18.18604222},
{"learn":[3.321540896],"iteration":945,"passed_time":312.7341809,"remaining_time":17.851634},
{"learn":[3.32129827],"iteration":946,"passed_time":312.8971245,"remaining_time":17.51166589},
{"learn":[3.321114533],"iteration":947,"passed_time":313.1027353,"remaining_time":17.17441164},
{"learn":[3.320941435],"iteration":948,"passed_time":313.3271088,"remaining_time":16.83844315},
{"learn":[3.320754476],"iteration":949,"passed_time":313.484661,"remaining_time":16.49919268},
{"learn":[3.320581212],"iteration":950,"passed_time":313.7690067,"remaining_time":16.16685734},
{"learn":[3.320403508],"iteration":951,"passed_time":313.9979097,"remaining_time":15.83182738},
{"learn":[3.320288574],"iteration":952,"passed_time":314.184774,"remaining_time":15.49494688},
{"learn":[3.320152124],"iteration":953,"passed_time":314.4304303,"remaining_time":15.16121572},
{"learn":[3.319884463],"iteration":954,"passed_time":314.6370478,"remaining_time":14.82582948},
{"learn":[3.319676144],"iteration":955,"passed_time":314.8861864,"remaining_time":14.49266967},
{"learn":[3.319554226],"iteration":956,"passed_time":315.1639546,"remaining_time":14.16097184},
{"learn":[3.319430379],"iteration":957,"passed_time":315.363997,"remaining_time":13.82597899},
{"learn":[3.319214533],"iteration":958,"passed_time":315.5833949,"remaining_time":13.49209509},
{"learn":[3.319048269],"iteration":959,"passed_time":315.8795063,"remaining_time":13.1616461},
{"learn":[3.318933341],"iteration":960,"passed_time":316.105577,"remaining_time":12.82842612},
{"learn":[3.318720177],"iteration":961,"passed_time":316.3525646,"remaining_time":12.49625515},
{"learn":[3.318521766],"iteration":962,"passed_time":316.6393082,"remaining_time":12.16578858},
{"learn":[3.318251659],"iteration":963,"passed_time":316.90765,"remaining_time":11.83472552},
{"learn":[3.318033948],"iteration":964,"passed_time":317.201213,"remaining_time":11.50470721},
{"learn":[3.317901683],"iteration":965,"passed_time":317.4591969,"remaining_time":11.17351211},
{"learn":[3.317758729],"iteration":966,"passed_time":317.6597379,"remaining_time":10.84050812},
{"learn":[3.31763706],"iteration":967,"passed_time":317.8595735,"remaining_time":10.5077545},
{"learn":[3.317492579],"iteration":968,"passed_time":318.0297378,"remaining_time":10.17432598},
{"learn":[3.317331879],"iteration":969,"passed_time":318.206449,"remaining_time":9.841436567},
{"learn":[3.317231038],"iteration":970,"passed_time":318.4568964,"remaining_time":9.511071056},
{"learn":[3.316914187],"iteration":971,"passed_time":318.6698188,"remaining_time":9.17978902},
{"learn":[3.316735087],"iteration":972,"passed_time":318.8537484,"remaining_time":8.847945743},
{"learn":[3.316624707],"iteration":973,"passed_time":319.0185212,"remaining_time":8.515894816},
{"learn":[3.316548886],"iteration":974,"passed_time":319.1973534,"remaining_time":8.184547522},
{"learn":[3.316422324],"iteration":975,"passed_time":319.384307,"remaining_time":7.853712467},
{"learn":[3.316276556],"iteration":976,"passed_time":319.5573723,"remaining_time":7.522844997},
{"learn":[3.316035823],"iteration":977,"passed_time":319.7472995,"remaining_time":7.192679538},
{"learn":[3.315899738],"iteration":978,"passed_time":319.9765693,"remaining_time":6.863644489},
{"learn":[3.315666231],"iteration":979,"passed_time":320.1926072,"remaining_time":6.534543004},
{"learn":[3.315534756],"iteration":980,"passed_time":320.5009297,"remaining_time":6.207459393},
{"learn":[3.315283073],"iteration":981,"passed_time":320.7119408,"remaining_time":5.87863028},
{"learn":[3.315179661],"iteration":982,"passed_time":320.9201346,"remaining_time":5.549992155},
{"learn":[3.314944504],"iteration":983,"passed_time":321.1081953,"remaining_time":5.221271468},
{"learn":[3.314866711],"iteration":984,"passed_time":321.2965346,"remaining_time":4.892840628},
{"learn":[3.314682594],"iteration":985,"passed_time":321.4598413,"remaining_time":4.564338517},
{"learn":[3.314514248],"iteration":986,"passed_time":321.6810632,"remaining_time":4.236933963},
{"learn":[3.314311125],"iteration":987,"passed_time":321.8803065,"remaining_time":3.909477407},
{"learn":[3.31406425],"iteration":988,"passed_time":322.1125633,"remaining_time":3.582647317},
{"learn":[3.313943512],"iteration":989,"passed_time":322.2975598,"remaining_time":3.255530907},
{"learn":[3.313648811],"iteration":990,"passed_time":322.5432718,"remaining_time":2.929252721},
{"learn":[3.313525087],"iteration":991,"passed_time":322.7779447,"remaining_time":2.603047941},
{"learn":[3.313434576],"iteration":992,"passed_time":323.0187593,"remaining_time":2.277070811},
{"learn":[3.313182988],"iteration":993,"passed_time":323.3043252,"remaining_time":1.951535162},
{"learn":[3.313032456],"iteration":994,"passed_time":323.4693919,"remaining_time":1.625474331},
{"learn":[3.312794073],"iteration":995,"passed_time":323.6271403,"remaining_time":1.299707391},
{"learn":[3.312611412],"iteration":996,"passed_time":323.8186609,"remaining_time":0.9743791201},
{"learn":[3.312268832],"iteration":997,"passed_time":323.9982863,"remaining_time":0.6492951628},
{"learn":[3.312108502],"iteration":998,"passed_time":324.2088346,"remaining_time":0.324533368},
{"learn":[3.311877605],"iteration":999,"passed_time":324.3891524,"remaining_time":0}
]}